{"ResponseStatus":{"Timestamp":"/Date(1621911514075+0800)/","Ack":"Success","Errors":[],"Extension":[{"Id":"CLOGGING_TRACE_ID","Value":"6597362056307780702"},{"Id":"RootMessageId","Value":"100025527-0a19d579-450530-6184474"}]},"Response":{"ReviewBaseInfo":{"categoryScore":[{"scoreName":"环境","itemScore":"4.5"},{"scoreName":"卫生","itemScore":"4.6"},{"scoreName":"服务","itemScore":"4.6"},{"scoreName":"设施","itemScore":"4.6"}],"recommendPercent":"95%推荐度","score":"4.6","totalReviews":1251,"scoreMax":5,"totalReviewsTA":0,"scoreDesc":"好","allTotalReviews":0,"ctripTotalReviews":1251,"ctripTotalReviewsForPage":1025,"totalUnusefulReviewsForPage":0},"ReviewList":[{"userProfile":{"avatarUrl":"//ak-d.tripcdn.com/images/t1/headphoto/424/398/503/0386f569fd0d4b488ff41b64bbc5743b_R_100_100_R5_Q70_D.jpg","userName":"_WeChat58633****","reviewedCount":2},"reviewDetails":{"reviewScore":{"score":"5","scoreMax":"5","scoreDescription":"超棒"},"reviewContent":"服务很不错，","releaseDate":"2019-08-20","travelType":"商务出差","roomType":"豪华标准房","checkInDate":"2019-08-17","feedbackList":[{"reviewId":"376109366","type":3,"createDate":"2019-08-21","content":"“简单而不简单，低调却不失内涵”，期待我们再次相遇，小瑞等您回家。"}],"sourceText":""},"reviewId":"375912621","helpfulCount":0,"markUseful":true,"showFold":false},{"userProfile":{"avatarUrl":"//ak-d.tripcdn.com/images/t1/headphoto/699/910/854/683dab66bb374136af9930ea204dfc7e_R_100_100_R5_Q70_D.jpg","userName":"M348191****","reviewedCount":1},"reviewDetails":{"reviewScore":{"score":"5","scoreMax":"5","scoreDescription":"超棒"},"reviewContent":"服务很好的","releaseDate":"2019-08-28","travelType":"代人预订","roomType":"经济标准间","checkInDate":"2019-08-15","feedbackList":[{"reviewId":"377655380","type":3,"createDate":"2019-08-29","content":"春风十里，不如小瑞等您，小瑞期待您下一次的不期而遇！"}],"sourceText":""},"reviewId":"377404626","helpfulCount":0,"markUseful":true,"showFold":false},{"userProfile":{"avatarUrl":"//ak-d.tripcdn.com/images/t1/headphoto/295/828/780/6e6c2151ed65497c850945d5d2b702ae_R_100_100_R5_Q70_D.jpg","userName":"中国安徽","reviewedCount":2},"reviewDetails":{"reviewScore":{"score":"5","scoreMax":"5","scoreDescription":"超棒"},"reviewContent":"接送很方便，服务也很好","releaseDate":"2019-11-24","travelType":"商务出差","roomType":"豪华标准房","checkInDate":"2019-02-14","feedbackList":[{"reviewId":"393189767","type":3,"createDate":"2019-11-26","content":"每个满意的话语，都是一份赞美与鼓励，能得到客官的夸奖是我们最大的满足，小伙伴们都期待您的下次光临哦！"}],"sourceText":""},"reviewId":"392751266","helpfulCount":0,"markUseful":true,"showFold":false},{"userProfile":{"avatarUrl":"//ak-d.tripcdn.com/images/Z80p180000013uw9yF21F_R_100_100_R5_Q70_D.jpg","userName":"z204****","reviewedCount":33},"reviewDetails":{"reviewScore":{"score":"5","scoreMax":"5","scoreDescription":"超棒"},"reviewContent":"性价比很高。。。","releaseDate":"2019-08-17","travelType":"商务出差","roomType":"豪华标准房","checkInDate":"2019-08-15","feedbackList":[{"reviewId":"375707609","type":3,"createDate":"2019-08-19","content":"“简单而不简单，低调却不失内涵”，期待我们再次相遇，小瑞等您回家。"}],"sourceText":""},"reviewId":"375120551","helpfulCount":0,"markUseful":true,"showFold":false},{"userProfile":{"avatarUrl":"//ak-d.tripcdn.com/images/Z80q12000000rqw5zE6ED_R_100_100_R5_Q70_D.jpg","userName":"张226600","reviewedCount":2},"reviewDetails":{"reviewScore":{"score":"5","scoreMax":"5","scoreDescription":"超棒"},"reviewContent":"早餐挺好的","releaseDate":"2019-08-15","travelType":"家庭亲子","roomType":"经济标准间","checkInDate":"2019-08-13","feedbackList":[{"reviewId":"375704281","type":3,"createDate":"2019-08-19","content":"时光如水，总是无言，您若安好，小瑞每天都是睛天，感谢您对小瑞的夸赞，我们相约下次再见"}],"sourceText":""},"reviewId":"374767606","helpfulCount":0,"markUseful":true,"showFold":false},{"userProfile":{"avatarUrl":"//ak-d.tripcdn.com/images/Z80p0j000000a67cwB846_R_100_100_R5_Q70_D.jpg","userName":"M232215****","reviewedCount":16},"reviewDetails":{"reviewScore":{"score":"5","scoreMax":"5","scoreDescription":"超棒"},"reviewContent":"都非常好，非常值得推荐。","releaseDate":"2019-05-02","travelType":"商务出差","roomType":"豪华标准房","checkInDate":"2019-02-14","feedbackList":[{"reviewId":"316424758","type":3,"createDate":"2019-05-08","content":"尊敬的宾客：感谢您百忙之中给予酒店的点评，您的点评意见对我们很重要，感恩您的支持和认可，您的满意是酒店全体员工，工作的最终目标，期待您的再次做客温州中瑞大酒店，在此祝您和您的家人生活幸福安康！"}],"sourceText":""},"reviewId":"314971714","helpfulCount":0,"markUseful":true,"showFold":false},{"userProfile":{"avatarUrl":"//ak-d.tripcdn.com/images/fd/headphoto/g2/M03/8D/83/Cghzf1VxbX-AG-s2AAENzHHNxGs587_R_100_100_R5_Q70_D.jpg","userName":"超有前途","reviewedCount":148},"reviewDetails":{"reviewScore":{"score":"5","scoreMax":"5","scoreDescription":"超棒"},"reviewContent":"非常好，服务好","releaseDate":"2019-07-01","travelType":"商务出差","roomType":"豪华大床房","checkInDate":"2019-06-26","feedbackList":[{"reviewId":"367356590","type":3,"createDate":"2019-07-02","content":"陪伴是最长情的告白，小瑞心怀感激，谢谢您与小瑞一路相随。"}],"sourceText":""},"reviewId":"367230667","helpfulCount":0,"markUseful":true,"showFold":false},{"userProfile":{"avatarUrl":"//ak-d.tripcdn.com/images/Z80p180000013uw9yF21F_R_100_100_R5_Q70_D.jpg","userName":"203792****","reviewedCount":177},"reviewDetails":{"reviewScore":{"score":"3","scoreMax":"5","scoreDescription":""},"reviewContent":"交通方便，整洁干净","releaseDate":"2019-06-19","travelType":"商务出差","roomType":"经济标准间","checkInDate":"2019-04-10","feedbackList":[{"reviewId":"365554232","type":3,"createDate":"2019-06-20","content":"尊敬的宾客：您好！非常感谢您选择下榻温州中瑞大酒店。你认可无疑是对我们最大的鼓励。我们将会更加努力把细节做的更好，宾客的满意是酒店全体员工工作的最终目标，再次感谢您的宝贵时间和反馈，期待您的再次做客温州中瑞大酒店，在此祝您和您的家人生活幸福安康！"}],"sourceText":""},"reviewId":"365429843","helpfulCount":0,"markUseful":true,"showFold":false},{"userProfile":{"avatarUrl":"//ak-d.tripcdn.com/images/Z80p180000013uw9yF21F_R_100_100_R5_Q70_D.jpg","userName":"M13293****","reviewedCount":12},"reviewDetails":{"reviewScore":{"score":"4.5","scoreMax":"5","scoreDescription":"不错"},"reviewContent":"周围有点乱，有点吵","releaseDate":"2019-05-14","travelType":"其他","roomType":"豪华大床房","checkInDate":"2019-04-10","feedbackList":[{"reviewId":"328312405","type":3,"createDate":"2019-05-19","content":"尊敬的宾客，您好！非常感谢您对我们酒店的选择，因为我们酒店后面是个市场，给你带来不愉快的入住体验抱歉，同时很感谢您的宝贵意见和建议，我们会努力改进，为您提供满意的服务是我们的职责，期待您的再次光临，我们会为您提供更优质的服务! "}],"sourceText":""},"reviewId":"317616157","helpfulCount":0,"markUseful":true,"showFold":false},{"userProfile":{"avatarUrl":"//ak-d.tripcdn.com/images/t1/headphoto/882/320/089/158cae5ddb6143c0b6ae18523614cf08_R_100_100_R5_Q70_D.jpg","userName":"华尔街1314","reviewedCount":5},"reviewDetails":{"reviewScore":{"score":"5","scoreMax":"5","scoreDescription":"超棒"},"reviewContent":"新的房间 不错","releaseDate":"2019-07-25","travelType":"独自旅行","roomType":"经济标准间","checkInDate":"2019-06-19","feedbackList":[{"reviewId":"371095864","type":3,"createDate":"2019-07-26","content":"时光静好，与君语。细水长流，与君同。繁花落尽，与君老。"}],"sourceText":""},"reviewId":"370843109","helpfulCount":0,"markUseful":true,"showFold":false},{"userProfile":{"avatarUrl":"//ak-d.tripcdn.com/images/fd/headphoto/g3/M05/AA/46/CggYG1ZBeoyAMFlDAAAZA_Udtb0602_R_100_100_R5_Q70_D.jpg","userName":"liujun****","reviewedCount":8},"reviewDetails":{"reviewScore":{"score":"5","scoreMax":"5","scoreDescription":"超棒"},"reviewContent":"环境早餐都好","releaseDate":"2019-06-21","travelType":"商务出差","roomType":"经济标准间","checkInDate":"2019-06-20","feedbackList":[{"reviewId":"366965182","type":3,"createDate":"2019-06-30","content":"简简单单的几个字，表达出您对小瑞如此的厚爱，小季一定会加倍努力做到更好！"}],"sourceText":""},"reviewId":"365820193","helpfulCount":0,"markUseful":true,"showFold":false},{"userProfile":{"avatarUrl":"//ak-d.tripcdn.com/images/t1/headphoto/646/318/109/a865fe5f5465407d8befd5dc487a8554_R_100_100_R5_Q70_D.jpg","userName":"M47354****","reviewedCount":11},"reviewDetails":{"reviewScore":{"score":"5","scoreMax":"5","scoreDescription":"超棒"},"reviewContent":"临时出差。还不错。","releaseDate":"2019-07-27","travelType":"商务出差","roomType":"豪华标准房","checkInDate":"2019-05-11","feedbackList":[{"reviewId":"371350621","type":3,"createDate":"2019-07-28","content":"相遇是最美好的歌，祝好！"}],"sourceText":""},"reviewId":"371180678","helpfulCount":0,"markUseful":true,"showFold":false},{"userProfile":{"avatarUrl":"//ak-d.tripcdn.com/images/Z80p180000013uw9yF21F_R_100_100_R5_Q70_D.jpg","userName":"_cm1390157****","reviewedCount":6},"reviewDetails":{"reviewScore":{"score":"3.8","scoreMax":"5","scoreDescription":""},"reviewContent":"有麻将桌的房间地上好脏","releaseDate":"2019-03-20","travelType":"商务出差","roomType":"豪华标准房","checkInDate":"2019-01-11","feedbackList":[{"reviewId":"273531713","type":3,"createDate":"2019-03-24","content":"敬的宾客：您好！非常感谢您选择下榻温州中瑞大酒店。感谢您告知我们在您入住本酒店期间所遇到的问题，很抱歉没能带给您更佳的入住体验，请允许我们向您表达最诚挚的歉意，谢谢您的反馈，我们将第一时间加强房间卫生的检查，客房是酒店的重要环节，对于卫生情况及客房状况，你的认可，无疑是对我们最大的鼓励。我们会更加努力，宾客最大的满意是酒店全体员工工作的最终目标，希望下次能获取你五星的好评，期待您的再次做客温州中瑞大酒店，在此祝您和您的家人生活幸福安康！"}],"sourceText":""},"reviewId":"273057089","helpfulCount":0,"markUseful":true,"showFold":false},{"userProfile":{"avatarUrl":"//ak-d.tripcdn.com/images/0Z84b1200086fs43y7BF4_R_100_100_R5_Q70_D.jpg","userName":"ASMLTrading","reviewedCount":15},"reviewDetails":{"reviewScore":{"score":"5","scoreMax":"5","scoreDescription":"超棒"},"reviewContent":"酒店设施等都非常好","releaseDate":"2019-03-16","travelType":"朋友出游","roomType":"豪华大床房","checkInDate":"2019-02-27","feedbackList":[{"reviewId":"272511317","type":3,"createDate":"2019-03-16","content":"敬的宾客：您好！非常感谢您选择下榻温州中瑞大酒店。看到您给我们五星的好评，心里非常温暖，你的高度认可，无疑是对我们最大的鼓励。我们会更加努力，宾客最大的满意是酒店全体员工工作的最终目标，期待您的再次做客温州中瑞大酒店，在此祝您和您的家人生活幸福安康！"}],"sourceText":""},"reviewId":"272506807","helpfulCount":0,"markUseful":true,"showFold":false},{"userProfile":{"avatarUrl":"//ak-d.tripcdn.com/images/t1/headphoto/982/089/752/f8c7b21182c94524ac4df328fdc7b3dc_R_100_100_R5_Q70_D.jpg","userName":"Lokm","reviewedCount":6},"reviewDetails":{"reviewScore":{"score":"4.8","scoreMax":"5","scoreDescription":"棒"},"reviewContent":"下高速就是","releaseDate":"2019-08-08","travelType":"商务出差","roomType":"经济标准间","checkInDate":"2019-08-03","feedbackList":[{"reviewId":"374166295","type":3,"createDate":"2019-08-12","content":"亲爱的君上，没能获取您5星的认可，可能是小瑞还有什么地方不够好，不管在哪了里在什么时候，小瑞期盼您归来的心依旧不变，愿您开心每一天！"}],"sourceText":""},"reviewId":"373295763","helpfulCount":0,"markUseful":true,"showFold":false},{"userProfile":{"avatarUrl":"//ak-d.tripcdn.com/images/Z80p180000013uw9yF21F_R_100_100_R5_Q70_D.jpg","userName":"xuyouli666","reviewedCount":2},"reviewDetails":{"reviewScore":{"score":"5","scoreMax":"5","scoreDescription":"超棒"},"reviewContent":"早餐不错，房间干净又大","releaseDate":"2019-03-24","travelType":"家庭亲子","roomType":"豪华标准房","checkInDate":"2019-01-29","feedbackList":[{"reviewId":"273522002","type":3,"createDate":"2019-03-24","content":"敬的宾客：您好！非常感谢您选择下榻温州中瑞大酒店。看到您给我们五星的好评，心里非常温暖，你的高度认可，无疑是对我们最大的鼓励。我们会更加努力，宾客最大的满意是酒店全体员工工作的最终目标，期待您的再次做客温州中瑞大酒店，在此祝您和您的家人生活幸福安康！"}],"sourceText":""},"reviewId":"273518302","helpfulCount":0,"markUseful":true,"showFold":false},{"userProfile":{"avatarUrl":"//ak-d.tripcdn.com/images/0Z81z120001xes050E5F9_R_100_100_R5_Q70_D.jpg","userName":"贪轮回","reviewedCount":4},"reviewDetails":{"reviewScore":{"score":"3.8","scoreMax":"5","scoreDescription":""},"reviewContent":"房间味道很大","releaseDate":"2019-06-17","travelType":"朋友出游","roomType":"经济标准间","checkInDate":"2019-06-12","feedbackList":[{"reviewId":"365191013","type":3,"createDate":"2019-06-17","content":"尊敬的宾客：您好！感谢您百忙之中给予酒店的点评，我们很重视您的点评，此次入住体验未能达到您的预期值，我们深表歉意，入住期间有任何问题您可以随时联系我们的大堂经理，我们一定会在第一时间为您解决，我们会更加努力，宾客最大的满意是酒店全体员工，工作的最终目标，期待您的再次做客温州中瑞大酒店，在此祝您和您的家人生活幸福安康！"}],"sourceText":""},"reviewId":"365163229","helpfulCount":0,"markUseful":true,"showFold":false},{"userProfile":{"avatarUrl":"//ak-d.tripcdn.com/images/t1/headphoto/903/173/918/eb4b7bea9720440dac09eab89328ab00_R_100_100_R5_Q70_D.jpg","userName":"眼镜螳螂","reviewedCount":8},"reviewDetails":{"reviewScore":{"score":"4","scoreMax":"5","scoreDescription":""},"reviewContent":"设备设施一般。","releaseDate":"2019-10-08","travelType":"朋友出游","roomType":"经济标准间","checkInDate":"2019-06-13","feedbackList":[{"reviewId":"384844232","type":3,"createDate":"2019-10-11","content":"尊敬的宾客您好！非常感谢您选择入住我们酒店，酒店准备了很多种不同布局的房型以供不同客人的选择，您下次选择不同房型入住体验一下，感谢您做出评价！"}],"sourceText":""},"reviewId":"384240565","helpfulCount":0,"markUseful":true,"showFold":false},{"userProfile":{"avatarUrl":"//ak-d.tripcdn.com/images/Z80p180000013uw9yF21F_R_100_100_R5_Q70_D.jpg","userName":"118943****","reviewedCount":5},"reviewDetails":{"reviewScore":{"score":"5","scoreMax":"5","scoreDescription":"超棒"},"reviewContent":"很不错啊啊啊","releaseDate":"2019-06-17","travelType":"商务出差","roomType":"经济标准间","checkInDate":"2019-06-16","feedbackList":[{"reviewId":"365290776","type":3,"createDate":"2019-06-18","content":"尊敬的宾客：您好！非常感谢您选择下榻温州中瑞大酒店。你的高度认可，无疑是对我们最大的鼓励。我们会更加努力，宾客最大的满意是酒店全体员工工作的最终目标，再次感谢您的宝贵时间和反馈，期待您的再次做客温州中瑞大酒店，在此祝您和您的家人生活幸福安康！"}],"sourceText":""},"reviewId":"365233885","helpfulCount":0,"markUseful":true,"showFold":false},{"userProfile":{"avatarUrl":"//ak-d.tripcdn.com/images/fd/headphoto/g5/M0A/4A/22/CggYsVay8tiAZRPrAAAX-vROloo046_R_100_100_R5_Q70_D.jpg","userName":"_CFT010000001155****","reviewedCount":1},"reviewDetails":{"reviewScore":{"score":"5","scoreMax":"5","scoreDescription":"超棒"},"reviewContent":"性价比不错  房间很大","releaseDate":"2019-03-07","travelType":"其他","roomType":"豪华大床房","checkInDate":"2019-02-23","feedbackList":[{"reviewId":"271292128","type":3,"createDate":"2019-03-07","content":"敬的宾客：您好！非常感谢您选择下榻温州中瑞大酒店。看到您给我们五星的好评，心里非常温暖，你的高度认可，无疑是对我们最大的鼓励。我们会更加努力，宾客最大的满意是酒店全体员工工作的最终目标，期待您的再次做客温州中瑞大酒店，在此祝您和您的家人生活幸福安康！"}],"sourceText":""},"reviewId":"271273547","helpfulCount":0,"markUseful":true,"showFold":false},{"userProfile":{"avatarUrl":"//ak-d.tripcdn.com/images/t1/headphoto/272/077/772/76b262d0cc24492abc5c6784c903c2ab_R_100_100_R5_Q70_D.jpg","userName":"chencc","reviewedCount":2},"reviewDetails":{"reviewScore":{"score":"5","scoreMax":"5","scoreDescription":"超棒"},"reviewContent":"房间挺大的","releaseDate":"2019-08-05","travelType":"代人预订","roomType":"豪华大床房","checkInDate":"2019-07-27","feedbackList":[{"reviewId":"373171742","type":3,"createDate":"2019-08-07","content":"您好！感谢您的入住与点评，祝您生活愉快，期待与您的下一次相遇~"}],"sourceText":""},"reviewId":"372914879","helpfulCount":0,"markUseful":true,"showFold":false},{"userProfile":{"avatarUrl":"//ak-d.tripcdn.com/images/t1/headphoto/903/173/918/eb4b7bea9720440dac09eab89328ab00_R_100_100_R5_Q70_D.jpg","userName":"M27486****","reviewedCount":62},"reviewDetails":{"reviewScore":{"score":"5","scoreMax":"5","scoreDescription":"超棒"},"reviewContent":"可以，方便得很","releaseDate":"2019-06-10","travelType":"商务出差","roomType":"经济标准间","checkInDate":"2019-06-07","feedbackList":[{"reviewId":"364295986","type":3,"createDate":"2019-06-11","content":"尊敬的宾客：感谢您选择下榻温州中瑞大酒店。你对酒店的支持和认可，无疑是对我们最大的鼓励。我们会更加努力，宾客最大的满意是酒店全体员工，工作的最终目标，期待您的再次做客温州中瑞大酒店，在此祝您和您的家人生活幸福安康！"}],"sourceText":""},"reviewId":"364136453","helpfulCount":0,"markUseful":true,"showFold":false},{"userProfile":{"avatarUrl":"//ak-d.tripcdn.com/images/Z80p180000013uw9yF21F_R_100_100_R5_Q70_D.jpg","userName":"1397127****","reviewedCount":15},"reviewDetails":{"reviewScore":{"score":"5","scoreMax":"5","scoreDescription":"超棒"},"reviewContent":"非常棒非常不错","releaseDate":"2019-06-20","travelType":"商务出差","roomType":"经济标准间","checkInDate":"2019-04-27","feedbackList":[{"reviewId":"365930391","type":3,"createDate":"2019-06-22","content":"简单的赞美胜似那柔软绵绵的情话，为此，我们会大步向前"}],"sourceText":""},"reviewId":"365591337","helpfulCount":0,"markUseful":true,"showFold":false},{"userProfile":{"avatarUrl":"//ak-d.tripcdn.com/images/Z80p180000013uw9yF21F_R_100_100_R5_Q70_D.jpg","userName":"翱翔金雕","reviewedCount":6},"reviewDetails":{"reviewScore":{"score":"1.5","scoreMax":"5","scoreDescription":""},"reviewContent":"位置很偏僻","releaseDate":"2019-11-16","travelType":"家庭亲子","roomType":"豪华大床房","checkInDate":"2019-07-22","feedbackList":[{"reviewId":"395482783","type":3,"createDate":"2019-12-09","content":"尊敬的宾客：您好！感谢您百忙之中给予酒店的点评，我们很重视您的评价，此次入住体验未能达到您的预期值，我们深表歉意，温州南站距离酒店1.2公里路程，有免费专车接送提前1小时预约，酒店临近大西洋银泰城步行十分钟路程，期待您再次做客温州中瑞大酒店，在此祝您和您的家人生活幸福安康！"}],"sourceText":""},"reviewId":"391394775","helpfulCount":0,"markUseful":true,"showFold":false},{"userProfile":{"avatarUrl":"//ak-d.tripcdn.com/images/Z80a0m000000df1y20C66_R_100_100_R5_Q70_D.jpg","userName":"1365677****","reviewedCount":6},"reviewDetails":{"reviewScore":{"score":"5","scoreMax":"5","scoreDescription":"超棒"},"reviewContent":"挺好的 一直住","releaseDate":"2019-06-24","travelType":"朋友出游","roomType":"豪华大床房","checkInDate":"2019-06-01","feedbackList":[{"reviewId":"366370127","type":3,"createDate":"2019-06-25","content":"一半春光里的旅行，一半故事里的洒脱。茫茫人海我们相遇，时光静好，中瑞与您细水长流！"}],"sourceText":""},"reviewId":"366159511","helpfulCount":0,"markUseful":true,"showFold":false},{"userProfile":{"avatarUrl":"//ak-d.tripcdn.com/images/0Z8331200087h8sjyFEA7_R_100_100_R5_Q70_D.jpg","userName":"才貌双全马小白","reviewedCount":54},"reviewDetails":{"reviewScore":{"score":"5","scoreMax":"5","scoreDescription":"超棒"},"reviewContent":"酒店不错，卫生也好","releaseDate":"2019-04-21","travelType":"商务出差","roomType":"豪华大床房","checkInDate":"2019-03-17","feedbackList":[{"reviewId":"292460190","type":3,"createDate":"2019-04-22","content":"尊敬的宾客：感谢您选择下榻温州中瑞大酒店。我们衷心的希望您在酒店有一次愉快的旅行，看到您给我们5星的好评，我们非常幸福，你对酒店的支持和认可，无疑是对我们最大的鼓励。我们会更加努力，宾客最大的满意是酒店全体员工，工作的最终目标，期待您的再次做客温州中瑞大酒店，在此祝您和您的家人生活幸福安康！"}],"sourceText":""},"reviewId":"287804855","helpfulCount":0,"markUseful":true,"showFold":false},{"userProfile":{"avatarUrl":"//ak-d.tripcdn.com/images/Z80h180000013xc9e3F64_R_100_100_R5_Q70_D.jpg","userName":"汪霞615","reviewedCount":1},"reviewDetails":{"reviewScore":{"score":"5","scoreMax":"5","scoreDescription":"超棒"},"reviewContent":"不错，适合带孩子","releaseDate":"2019-04-21","travelType":"商务出差","roomType":"豪华大床房","checkInDate":"2019-04-19","feedbackList":[{"reviewId":"292461280","type":3,"createDate":"2019-04-22","content":"尊敬的宾客：感谢您选择下榻温州中瑞大酒店。我们衷心的希望您在酒店有一次愉快的旅行，看到您给我们5星的好评，我们非常幸福，你对酒店的支持和认可，无疑是对我们最大的鼓励。我们会更加努力，宾客最大的满意是酒店全体员工，工作的最终目标，期待您的再次做客温州中瑞大酒店，在此祝您和您的家人生活幸福安康！"}],"sourceText":""},"reviewId":"287241193","helpfulCount":0,"markUseful":true,"showFold":false},{"userProfile":{"avatarUrl":"//ak-d.tripcdn.com/images/Z805090000003sk8xBF92_R_100_100_R5_Q70_D.jpg","userName":"许洪斌","reviewedCount":38},"reviewDetails":{"reviewScore":{"score":"4.5","scoreMax":"5","scoreDescription":"不错"},"reviewContent":"不错，早餐9点就关闭了。","releaseDate":"2019-02-08","travelType":"朋友出游","roomType":"豪华标准房","checkInDate":"2019-02-06","feedbackList":[{"reviewId":"268091030","type":3,"createDate":"2019-02-14","content":"敬的宾客：您好！非常感谢您选择下榻温州中瑞大酒店。看到您给我们的好评，无疑是对我们最大的鼓励。我们会更加努力，宾客最大的满意是酒店全体员工工作的最终目标，再次感谢您的宝贵时间和反馈，力争下次做到你五星的认可，期待您的再次做客温州中瑞大酒店，在此祝您和您的家人生活幸福安康"}],"sourceText":""},"reviewId":"266881191","helpfulCount":0,"markUseful":true,"showFold":false},{"userProfile":{"avatarUrl":"//ak-d.tripcdn.com/images/Z80p180000013uw9yF21F_R_100_100_R5_Q70_D.jpg","userName":"M11019****","reviewedCount":1},"reviewDetails":{"reviewScore":{"score":"5","scoreMax":"5","scoreDescription":"超棒"},"reviewContent":"早餐很不错","releaseDate":"2019-07-21","travelType":"商务出差","roomType":"豪华大床房","checkInDate":"2019-07-11","feedbackList":[{"reviewId":"370404449","type":3,"createDate":"2019-07-22","content":"不忘初心是我们服务的本质，小瑞这厢有礼啦~小瑞，是您出门不二选择，期待您的再次入住哟"}],"sourceText":""},"reviewId":"370213631","helpfulCount":0,"markUseful":true,"showFold":false},{"userProfile":{"avatarUrl":"//ak-d.tripcdn.com/images/t1/headphoto/531/193/945/c1dc713021cd4cc3ad8db80c93b61ede_R_100_100_R5_Q70_D.jpg","userName":"CorinChen","reviewedCount":38},"reviewDetails":{"reviewScore":{"score":"5","scoreMax":"5","scoreDescription":"超棒"},"reviewContent":"还可以！离高铁近","releaseDate":"2019-05-30","travelType":"商务出差","roomType":"高级标准房","checkInDate":"2019-04-15","feedbackList":[{"reviewId":"355180296","type":3,"createDate":"2019-06-01","content":"尊敬的宾客：感谢您选择下榻温州中瑞大酒店。你对酒店的支持和认可，无疑是对我们最大的鼓励。我们会更加努力，宾客最大的满意是酒店全体员工，工作的最终目标，期待您的再次做客温州中瑞大酒店，在此祝您和您的家人生活幸福安康！"}],"sourceText":""},"reviewId":"349812836","helpfulCount":0,"markUseful":true,"showFold":false},{"userProfile":{"avatarUrl":"//ak-d.tripcdn.com/images/Z80h0b0000005rg6v11FC_R_100_100_R5_Q70_D.jpg","userName":"林凡恒","reviewedCount":48},"reviewDetails":{"reviewScore":{"score":"4","scoreMax":"5","scoreDescription":""},"reviewContent":"一般般啦.","releaseDate":"2019-11-09","travelType":"商务出差","roomType":"豪华大床房","checkInDate":"2019-09-04","feedbackList":[{"reviewId":"390801010","type":3,"createDate":"2019-11-11","content":"小瑞很抱歉，您此次入住没给您留下美好的体验，下次入住如您有任何为题都可拨打前台电话，我们会第一时间解决您所有问题，期待您的下次光临，祝您生活工作愉快~"}],"sourceText":""},"reviewId":"390434148","helpfulCount":0,"markUseful":true,"showFold":false},{"userProfile":{"avatarUrl":"//ak-d.tripcdn.com/images/t1/headphoto/882/320/089/158cae5ddb6143c0b6ae18523614cf08_R_100_100_R5_Q70_D.jpg","userName":"E60633****","reviewedCount":39},"reviewDetails":{"reviewScore":{"score":"3.3","scoreMax":"5","scoreDescription":""},"reviewContent":"一般一般一般一般","releaseDate":"2019-03-20","travelType":"商务出差","roomType":"豪华大床房","checkInDate":"2019-03-10","feedbackList":[{"reviewId":"273531809","type":3,"createDate":"2019-03-24","content":"敬的宾客：您好！非常感谢您选择下榻温州中瑞大酒店。看到您给我们的分数，心里有点伤心更有点遗憾，一定是我们的服务还不够好，没有达到你预期值，你的认可，无疑是对我们最大的鼓励。，我们会更加努力，宾客最大的满意是酒店全体员工工作的最终目标，希望下次能获取你五星的好评，期待您的再次做客温州中瑞大酒店，在此祝您和您的家人生活幸福安康！"}],"sourceText":""},"reviewId":"273052254","helpfulCount":0,"markUseful":true,"showFold":false},{"userProfile":{"avatarUrl":"//ak-d.tripcdn.com/images/fd/headphoto/g1/M07/F6/20/CghzfFUCRViAGsO_AAAct04HJFY025_R_100_100_R5_Q70_D.jpg","userName":"赛达荀勖","reviewedCount":3},"reviewDetails":{"reviewScore":{"score":"4","scoreMax":"5","scoreDescription":""},"reviewContent":"早餐还可以，服务周到","releaseDate":"2019-03-21","travelType":"家庭亲子","roomType":"豪华标准房","checkInDate":"2019-01-31","feedbackList":[{"reviewId":"273530580","type":3,"createDate":"2019-03-24","content":"敬的宾客：您好！非常感谢您选择下榻温州中瑞大酒店。看到您给我们的分数，心里有点伤心更有点遗憾，一定是我们的服务还不够好，没有达到你预期值，你的认可，无疑是对我们最大的鼓励。，我们会更加努力，宾客最大的满意是酒店全体员工工作的最终目标，希望下次能获取你五星的好评，期待您的再次做客温州中瑞大酒店，在此祝您和您的家人生活幸福安康！"}],"sourceText":""},"reviewId":"273199549","helpfulCount":0,"markUseful":true,"showFold":false},{"userProfile":{"avatarUrl":"//ak-d.tripcdn.com/images/t1/headphoto/258/512/704/6bce7506eecc48f8a4a6d3177e0acf24_R_100_100_R5_Q70_D.jpg","userName":"_WeChat255177****","reviewedCount":1},"reviewDetails":{"reviewScore":{"score":"4.8","scoreMax":"5","scoreDescription":"棒"},"reviewContent":"早饭都没吃","releaseDate":"2019-07-05","travelType":"商务出差","roomType":"经济标准间","checkInDate":"2019-07-04","feedbackList":[{"reviewId":"368201062","type":3,"createDate":"2019-07-08","content":"有种思念叫牵肠挂肚，有种约定叫天荒地老，有种幸福叫认识您真好，为了给您最好，小瑞一直在努力，期待您和朋友的光临！"}],"sourceText":""},"reviewId":"367765029","helpfulCount":0,"markUseful":true,"showFold":false},{"userProfile":{"avatarUrl":"//ak-d.tripcdn.com/images/Z80c1700000115vcw53CA_R_100_100_R5_Q70_D.jpg","userName":"1505029****","reviewedCount":9},"reviewDetails":{"reviewScore":{"score":"5","scoreMax":"5","scoreDescription":"超棒"},"reviewContent":"环境还可以","releaseDate":"2019-08-07","travelType":"商务出差","roomType":"经济标准间","checkInDate":"2019-07-03","feedbackList":[{"reviewId":"373197997","type":3,"createDate":"2019-08-07","content":"一句认可，胜过千言万语，感谢君对小瑞的支持！十分荣欣您能选择我们，期待您的下次光临！"}],"reviewVideos":[{"thumbnail":"http://video.c-ctrip.com/videos/23031700000114xy5B3E9_cover.jpg","video":"https://video.c-ctrip.com/videos/23031700000114xy5B3E9.mp4"}],"sourceText":""},"reviewId":"373175486","helpfulCount":0,"markUseful":true,"showFold":false},{"userProfile":{"avatarUrl":"//ak-d.tripcdn.com/images/Z80p180000013uw9yF21F_R_100_100_R5_Q70_D.jpg","userName":"五岳字图","reviewedCount":19},"reviewDetails":{"reviewScore":{"score":"5","scoreMax":"5","scoreDescription":"超棒"},"reviewContent":"早餐丰富多样","releaseDate":"2019-05-26","travelType":"家庭亲子","roomType":"豪华标准房","checkInDate":"2019-05-20","feedbackList":[{"reviewId":"342001068","type":3,"createDate":"2019-05-27","content":"尊敬的宾客：有种相识，在路上，有种相知，早已封存在心，只是路过的时候打开了那扇窗，彼此看到了那些风景，迎来了春暖花开。感恩您的支持和认可，您的满意是酒店全体员工，工作的最终目标，期待您的再次做客温州中瑞大酒店，在此祝您和您的家人生活幸福安康！"}],"sourceText":""},"reviewId":"341656087","helpfulCount":0,"markUseful":true,"showFold":false},{"userProfile":{"avatarUrl":"//ak-d.tripcdn.com/images/t1/headphoto/646/318/109/a865fe5f5465407d8befd5dc487a8554_R_100_100_R5_Q70_D.jpg","userName":"M248716****","reviewedCount":2},"reviewDetails":{"reviewScore":{"score":"5","scoreMax":"5","scoreDescription":"超棒"},"reviewContent":"房间大，还可以","releaseDate":"2019-05-21","travelType":"商务出差","roomType":"经济标准间","checkInDate":"2019-05-20","feedbackList":[{"reviewId":"341161471","type":3,"createDate":"2019-05-24","content":"尊敬的顾客您好！感谢您选择入住中瑞大酒店并给予五星好评！您的认可是我们最大的荣幸以及动力，让我们在今后的服务中不断提升、不断创新，能够给您带来更好的入住体验，竭诚欢迎您的下次入住！"}],"sourceText":""},"reviewId":"331517659","helpfulCount":0,"markUseful":true,"showFold":false},{"userProfile":{"avatarUrl":"//ak-d.tripcdn.com/images/fd/headphoto/g5/M05/A8/C5/CggYsFajbO6ASHZnAAAYv5ys_Nk016_R_100_100_R5_Q70_D.jpg","userName":"马利堡","reviewedCount":22},"reviewDetails":{"reviewScore":{"score":"5","scoreMax":"5","scoreDescription":"超棒"},"reviewContent":"地方很好，出很方便","releaseDate":"2019-05-02","travelType":"商务出差","roomType":"豪华标准房","checkInDate":"2019-03-03","feedbackList":[{"reviewId":"315649495","type":3,"createDate":"2019-05-05","content":"尊敬的宾客：感谢您选择下榻温州中瑞大酒店。十分欣喜能获取您5星的满意，你对酒店的支持和认可，无疑是对我们最大的鼓励。我们会更加努力，宾客最大的满意是酒店全体员工，工作的最终目标，期待您的再次做客温州中瑞大酒店，在此祝您和您的家人生活幸福安康！"}],"sourceText":""},"reviewId":"314930410","helpfulCount":0,"markUseful":true,"showFold":false},{"userProfile":{"avatarUrl":"//ak-d.tripcdn.com/images/Z80f15000000yjfz6158C_R_100_100_R5_Q70_D.jpg","userName":"bingice0703","reviewedCount":42},"reviewDetails":{"reviewScore":{"score":"4","scoreMax":"5","scoreDescription":""},"reviewContent":"非常好 干净舒适","releaseDate":"2019-06-22","travelType":"商务出差","roomType":"豪华大床房","checkInDate":"2019-04-06","feedbackList":[{"reviewId":"365930553","type":3,"createDate":"2019-06-22","content":"将心比心，用我们的爱心、诚心、细心，换您的舒心、放心、安心。"}],"sourceText":""},"reviewId":"365891577","helpfulCount":0,"markUseful":true,"showFold":false},{"userProfile":{"avatarUrl":"//ak-d.tripcdn.com/images/Z808080000003htomDAB6_R_100_100_R5_Q70_D.jpg","userName":"Runner","reviewedCount":25},"reviewDetails":{"reviewScore":{"score":"4.3","scoreMax":"5","scoreDescription":""},"reviewContent":"位置偏了点","releaseDate":"2019-12-03","travelType":"商务出差","roomType":"经济标准间","checkInDate":"2019-06-25","feedbackList":[{"reviewId":"394956364","type":3,"createDate":"2019-12-06","content":"亲爱的宾客，您好！十分感谢您入住温州中瑞大酒店和我们分享您的感受。我们酒店为了方便客人免费接送站服务（7.30~23:00需提前一小时致电酒店进行预约哦~），非常适合出差旅游的客人，我们一直坚持以创造客户价值为中心，不断提升自身价值，为顾客带来更好的入住体验和入住环境。期待您的下次光临！"}],"sourceText":""},"reviewId":"394404946","helpfulCount":0,"markUseful":true,"showFold":false},{"userProfile":{"avatarUrl":"//ak-d.tripcdn.com/images/1h61z120008m01mwqE2D9_R_100_100_R5_Q70_D.jpg","userName":"M19531****","reviewedCount":7},"reviewDetails":{"reviewScore":{"score":"4.8","scoreMax":"5","scoreDescription":"棒"},"reviewContent":"早餐挺满意的","releaseDate":"2019-08-05","travelType":"商务出差","roomType":"经济标准间","checkInDate":"2019-05-08","feedbackList":[{"reviewId":"373172258","type":3,"createDate":"2019-08-07","content":"您好！感谢您的入住与点评，我们的早餐是中西结合式自助早餐，种类丰盛，很感谢您的满意，您的满意鞭策着我们继续进步，期待与您的再次相遇~"}],"sourceText":""},"reviewId":"372744525","helpfulCount":0,"markUseful":true,"showFold":false},{"userProfile":{"avatarUrl":"//ak-d.tripcdn.com/images/t1/headphoto/295/828/780/6e6c2151ed65497c850945d5d2b702ae_R_100_100_R5_Q70_D.jpg","userName":"_WeChat303038****","reviewedCount":9},"reviewDetails":{"reviewScore":{"score":"3.5","scoreMax":"5","scoreDescription":""},"reviewContent":"下次不住这里。","releaseDate":"2019-05-09","travelType":"商务出差","roomType":"高级标准房","checkInDate":"2019-05-08","feedbackList":[{"reviewId":"316964982","type":3,"createDate":"2019-05-11","content":"尊敬的宾客：您好！我们的服务宗旨是一贯以顾客满意为最终目标，非常遗憾未能达到您的预期值，我们向您表示最诚挚地歉意，同时我们将极力改善服务管理上的不到之处，在这里也希望您能再给我们一次机会，诚挚邀请您再一次地入住，我们会竭诚为您服务，给您一次满意、舒心的入住体验，希望在不久的将来有机会为您奉上更好的服务体验，期待您的再次做客温州中瑞大酒店，祝您生活幸福安康！"}],"sourceText":""},"reviewId":"316589856","helpfulCount":0,"markUseful":true,"showFold":false},{"userProfile":{"avatarUrl":"//ak-d.tripcdn.com/images/t1/headphoto/272/077/772/76b262d0cc24492abc5c6784c903c2ab_R_100_100_R5_Q70_D.jpg","userName":"M274611****","reviewedCount":21},"reviewDetails":{"reviewScore":{"score":"5","scoreMax":"5","scoreDescription":"超棒"},"reviewContent":"位置好，服务好","releaseDate":"2019-08-05","travelType":"商务出差","roomType":"经济标准间","checkInDate":"2019-05-13","feedbackList":[{"reviewId":"373171825","type":3,"createDate":"2019-08-07","content":"您好！感谢您的入住与点评，我们酒店毗邻温州动车南站，交通十分便利，斜对面就是大西洋银泰城，购物吃饭娱乐集一体，是您出差商旅的最佳选择，期待您的再次光临并祝您生活愉快！"}],"sourceText":""},"reviewId":"372908078","helpfulCount":0,"markUseful":true,"showFold":false},{"userProfile":{"avatarUrl":"//ak-d.tripcdn.com/images/Z80p180000013uw9yF21F_R_100_100_R5_Q70_D.jpg","userName":"109699****","reviewedCount":20},"reviewDetails":{"reviewScore":{"score":"4","scoreMax":"5","scoreDescription":""},"reviewContent":"位置偏僻，床不舒服","releaseDate":"2019-07-10","travelType":"商务出差","roomType":"豪华大床房","checkInDate":"2019-02-25","feedbackList":[{"reviewId":"368607208","type":3,"createDate":"2019-07-11","content":"一花一世界，一叶一追寻。一曲一场叹，一生为一人。做不足之处小瑞会努力改进，小主常来哦~"}],"sourceText":""},"reviewId":"368498597","helpfulCount":0,"markUseful":true,"showFold":false},{"userProfile":{"avatarUrl":"//ak-d.tripcdn.com/images/Z80p180000013uw9yF21F_R_100_100_R5_Q70_D.jpg","userName":"_CFT010000000106****","reviewedCount":7},"reviewDetails":{"reviewScore":{"score":"5","scoreMax":"5","scoreDescription":"超棒"},"reviewContent":"离车站近的","releaseDate":"2019-11-18","travelType":"商务出差","roomType":"经济标准间","checkInDate":"2019-06-19","feedbackList":[{"reviewId":"394965548","type":3,"createDate":"2019-12-06","content":"尊敬的宾客，您好。感谢您选择入住我们酒店并给予肯定，简单的话语足以给我们认可，感谢您的宝贵建议，我们会不懈前进，会不断的改善并创造更好的居住环境来满足宾客的需求。再次感谢您的支持与厚爱，希望您在住宿期间充满了快乐的回忆。祝您生活愉快并期待您的再次光临！"}],"sourceText":""},"reviewId":"391797957","helpfulCount":0,"markUseful":true,"showFold":false},{"userProfile":{"avatarUrl":"//ak-d.tripcdn.com/images/t1/headphoto/177/080/529/285e9abeede347d9a7c1cc5e1b4c9287_R_100_100_R5_Q70_D.jpg","userName":"_WeChat47380****","reviewedCount":6},"reviewDetails":{"reviewScore":{"score":"5","scoreMax":"5","scoreDescription":"超棒"},"reviewContent":"早餐不错的","releaseDate":"2019-07-19","travelType":"商务出差","roomType":"经济标准间","checkInDate":"2019-06-19","feedbackList":[{"reviewId":"370003236","type":3,"createDate":"2019-07-20","content":"您的满意，我们的动力，小瑞祝您生活愉快！"}],"sourceText":""},"reviewId":"369948069","helpfulCount":0,"markUseful":true,"showFold":false},{"userProfile":{"avatarUrl":"//ak-d.tripcdn.com/images/fd/headphoto/g3/M04/9D/B9/CggYGlYN5kqAOETNAAET3Df6e8M805_R_100_100_R5_Q70_D.jpg","userName":"沙漠鱼","reviewedCount":79},"reviewDetails":{"reviewScore":{"score":"5","scoreMax":"5","scoreDescription":"超棒"},"reviewContent":"交通便利，酒店住房干净","releaseDate":"2019-05-20","travelType":"商务出差","roomType":"豪华大床房","checkInDate":"2018-12-20","feedbackList":[{"reviewId":"341154381","type":3,"createDate":"2019-05-24","content":"尊敬的顾客您好！感谢您选择入住中瑞大酒店并给予五星好评，您的认可是我们最大的荣幸以及最大的动力，让我们在今后的服务中不断提升、不断创新。竭诚欢迎您的下次入住！"}],"sourceText":""},"reviewId":"330005235","helpfulCount":0,"markUseful":true,"showFold":false},{"userProfile":{"avatarUrl":"//ak-d.tripcdn.com/images/t1/headphoto/982/089/752/f8c7b21182c94524ac4df328fdc7b3dc_R_100_100_R5_Q70_D.jpg","userName":"我是亚诺","reviewedCount":4},"reviewDetails":{"reviewScore":{"score":"5","scoreMax":"5","scoreDescription":"超棒"},"reviewContent":"新开业的，环境好","releaseDate":"2019-03-24","travelType":"商务出差","roomType":"豪华大床房","checkInDate":"2019-03-21","feedbackList":[{"reviewId":"273595988","type":3,"createDate":"2019-03-24","content":"敬的宾客：您好！非常感谢您选择下榻温州中瑞大酒店。看到您给我们五星的好评，心里非常温暖，你的高度认可，无疑是对我们最大的鼓励。我们会更加努力，宾客最大的满意是酒店全体员工，工作的最终目标，期待您的再次做客温州中瑞大酒店，在此祝您和您的家人生活幸福安康！"}],"sourceText":""},"reviewId":"273547797","helpfulCount":0,"markUseful":true,"showFold":false},{"userProfile":{"avatarUrl":"//ak-d.tripcdn.com/images/Z80m11000000r30lzD37E_R_100_100_R5_Q70_D.jpg","userName":"T1anT1an","reviewedCount":13},"reviewDetails":{"reviewScore":{"score":"5","scoreMax":"5","scoreDescription":"超棒"},"reviewContent":"很满意的一次住宿","releaseDate":"2019-02-17","travelType":"家庭亲子","roomType":"豪华标准房","checkInDate":"2019-02-16","feedbackList":[{"reviewId":"269038719","type":3,"createDate":"2019-02-20","content":"尊敬的宾客：您好！非常感谢您选择下榻温州中瑞大酒店。看到您给我们五星的好评，心里非常温暖，你的高度认可，无疑是对我们最大的鼓励。我们会更加努力，宾客最大的满意是酒店全体员工工作的最终目标，再次感谢您的宝贵时间和反馈，期待您的再次做客温州中瑞大酒店，在此祝您和您的家人生活幸福安康！"}],"sourceText":""},"reviewId":"268637670","helpfulCount":0,"markUseful":true,"showFold":false},{"userProfile":{"avatarUrl":"//ak-d.tripcdn.com/images/fd/headphoto/g3/M0A/5E/E2/CggYG1azROSACBh1AAApjbBaRfk210_R_100_100_R5_Q70_D.jpg","userName":"安纳德吕蒙","reviewedCount":26},"reviewDetails":{"reviewScore":{"score":"5","scoreMax":"5","scoreDescription":"超棒"},"reviewContent":"离高铁站方便很干净","releaseDate":"2019-01-14","travelType":"商务出差","roomType":"豪华标准房","checkInDate":"2019-01-10","feedbackList":[{"reviewId":"264556629","type":3,"createDate":"2019-01-20","content":"尊敬的宾客：您好！非常感谢您选择下榻温州中瑞大酒店。看到您给我们五星的好评，心里非常温暖，你的高度认可，无疑是对我们最大的鼓励。我们会更加努力，宾客最大的满意是酒店全体员工工作的最终目标，再次感谢您的宝贵时间和反馈，期待您的再次做客温州中瑞大酒店，在此祝您和您的家人生活幸福安康！"}],"sourceText":""},"reviewId":"263812000","helpfulCount":0,"markUseful":true,"showFold":false}],"ReviewFilterList":[{"name":"全部","id":"1","type":"commonTheme","count":"1251"},{"name":"推荐","id":"2","type":"commonTheme","count":"1190"},{"name":"差评","id":"3","type":"commonTheme","count":"45"},{"name":"有图","id":"4","type":"commonTheme","count":"70"},{"name":"视频","id":"5","type":"commonTheme","count":"11"},{"name":"有图/视频","id":"6","type":"commonTheme","count":"77"},{"name":"早餐很棒","id":"70","type":"tagTheme","count":"157"},{"name":"房间很大","id":"29","type":"tagTheme","count":"76"},{"name":"近火车站","id":"95","type":"tagTheme","count":"57"},{"name":"提供接送","id":"101","type":"tagTheme","count":"46"},{"name":"房间不错","id":"25","type":"tagTheme","count":"41"},{"name":"停车方便","id":"80","type":"tagTheme","count":"34"},{"name":"前台热情","id":"84","type":"tagTheme","count":"34"},{"name":"适合出差","id":"136","type":"tagTheme","count":"17"},{"name":"所有房型","type":"roomType","count":"1025"},{"name":"豪华大床房","id":"1","type":"roomType","count":"312"},{"name":"中瑞特惠房","id":"2","type":"roomType","count":"154"},{"name":"豪华双床房","id":"3","type":"roomType","count":"39"},{"name":"家庭套房","id":"4","type":"roomType","count":"9"},{"name":"行政大床房","id":"5","type":"roomType","count":"9"},{"name":"中瑞三人房","id":"6","type":"roomType","count":"6"},{"name":"高级大床房","id":"7","type":"roomType","count":"5"},{"name":"健康智能睡眠大床房","id":"8","type":"roomType","count":"2"},{"name":"所有出游类型","type":"reviewTag"},{"name":"商务出差","id":"10","type":"reviewTag","count":"586"},{"name":"家庭亲子","id":"30","type":"reviewTag","count":"88"},{"name":"独自旅行","id":"50","type":"reviewTag","count":"41"},{"name":"代人预订","id":"60","type":"reviewTag","count":"12"},{"name":"情侣出游","id":"70","type":"reviewTag","count":"51"},{"name":"朋友出游","id":"40","type":"reviewTag","count":"65"},{"name":"其他","id":"0","type":"reviewTag","count":"392"}]},"ErrorCode":0}