{"ResponseStatus":{"Timestamp":"/Date(1621911541098+0800)/","Ack":"Success","Errors":[],"Extension":[{"Id":"CLOGGING_TRACE_ID","Value":"4702466695088653524"},{"Id":"RootMessageId","Value":"100025527-0a19abc5-450530-6233896"}]},"Response":{"ReviewBaseInfo":{"categoryScore":[{"scoreName":"环境","itemScore":"4.4"},{"scoreName":"卫生","itemScore":"4.5"},{"scoreName":"服务","itemScore":"4.5"},{"scoreName":"设施","itemScore":"4.4"}],"recommendPercent":"94%推荐度","score":"4.5","totalReviews":588,"scoreMax":5,"totalReviewsTA":0,"scoreDesc":"不错","allTotalReviews":0,"ctripTotalReviews":588,"ctripTotalReviewsForPage":486,"totalUnusefulReviewsForPage":0},"ReviewList":[{"userProfile":{"avatarUrl":"//ak-d.tripcdn.com/images/Z80h180000013xc9e3F64_R_100_100_R5_Q70_D.jpg","userName":"205360****","reviewedCount":1},"reviewDetails":{"reviewScore":{"score":"3","scoreMax":"5","scoreDescription":""},"reviewContent":"可以好可以","releaseDate":"2020-12-03","travelType":"商务出差","roomType":"特价大床房","checkInDate":"2020-11-29","feedbackList":[{"reviewId":"498070410","type":3,"createDate":"2021-05-13","content":"尊敬的贵宾您好！首先感谢您的光临，小云2021年现已全新装修升级为航空主题酒店，精选优质床品，主打高性价比，小云致力于让每一位宾客享有宾至如归的入住体验，期待为您的每一次温州之行提供物超所值的服务~祝您生活愉快~"}],"sourceText":""},"reviewId":"472434800","helpfulCount":0,"markUseful":true,"showFold":false},{"userProfile":{"avatarUrl":"//ak-d.tripcdn.com/images/fd/headphoto/g2/M02/A8/60/CghzgFTd0YyAW4-IAAAukHw2mO0893_R_100_100_R5_Q70_D.jpg","userName":"mmmwow","reviewedCount":25},"reviewDetails":{"reviewScore":{"score":"5","scoreMax":"5","scoreDescription":"超棒"},"reviewContent":"设施服务卫生什么的都还不错，就是位置一般，没有停车场","releaseDate":"2019-10-07","travelType":"家庭亲子","roomType":"豪华大床房","checkInDate":"2019-10-06","feedbackList":[{"reviewId":"385683749","type":3,"createDate":"2019-10-17","content":"尊敬的宾客：您好！感谢您选择入住温州荣欣楼大酒店，感谢您对我们服务的认可，期待您的再次光临！"}],"sourceText":""},"reviewId":"384051089","helpfulCount":0,"markUseful":true,"showFold":false},{"userProfile":{"avatarUrl":"//ak-d.tripcdn.com/images/Z80p180000013uw9yF21F_R_100_100_R5_Q70_D.jpg","userName":"M1969****","reviewedCount":19},"reviewDetails":{"reviewScore":{"score":"4.5","scoreMax":"5","scoreDescription":"不错"},"reviewContent":"挺好，服务员挺有礼貌。","releaseDate":"2020-06-13","travelType":"朋友出游","roomType":"特价大床房","checkInDate":"2020-06-09","feedbackList":[{"reviewId":"424523849","type":3,"createDate":"2020-07-18","content":"尊敬的宾客，非常感谢您对我们酒店的好评，我们会再接再厉不辜负您的好评。再次感谢您对酒店的肯定，期待再次光临，祝旅途愉快！"}],"sourceText":""},"reviewId":"419481359","helpfulCount":0,"markUseful":true,"showFold":false},{"userProfile":{"avatarUrl":"//ak-d.tripcdn.com/images/fd/headphoto/g1/M09/FF/5D/CghzfVTKXPOAffDLAADjRREasTI358_R_100_100_R5_Q70_D.jpg","userName":"ntzlp","reviewedCount":89},"reviewDetails":{"reviewScore":{"score":"4","scoreMax":"5","scoreDescription":""},"reviewContent":"服务要跟上","releaseDate":"2020-11-17","travelType":"商务出差","roomType":"特价双床房","checkInDate":"2020-11-16","feedbackList":[{"reviewId":"470340025","type":3,"createDate":"2020-11-19","content":"尊敬的宾客，感谢您对酒店的点评！非常感谢您宝贵的意见，我们会将意见告知相关部门以提高服务质量。若您下次至此，希望能再次预订本酒店，给我们一个机会致歉。期待再次光临！"}],"sourceText":""},"reviewId":"470072585","helpfulCount":0,"markUseful":true,"showFold":false},{"userProfile":{"avatarUrl":"//ak-d.tripcdn.com/images/Z80p180000013uw9yF21F_R_100_100_R5_Q70_D.jpg","userName":"M11897****","reviewedCount":4},"reviewDetails":{"reviewScore":{"score":"5","scoreMax":"5","scoreDescription":"超棒"},"reviewContent":"很超值的酒店，100多元享受的是五星级的服务，20元享受的是四星级的早餐！！！","releaseDate":"2019-08-13","travelType":"家庭亲子","roomType":"特价双床房","checkInDate":"2019-08-12","feedbackList":[{"reviewId":"375823240","type":3,"createDate":"2019-08-20","content":"尊敬的贵宾您好！感谢您选择入住荣欣楼大酒店。我们始终相信好的口碑一定是从客人最真诚的满意度推荐出来的。我们将不断努力为您及所有宾客提供更佳的入住感受。真诚期待您的再次光临！"}],"sourceText":""},"reviewId":"374443553","helpfulCount":0,"markUseful":true,"showFold":false},{"userProfile":{"avatarUrl":"//ak-d.tripcdn.com/images/t1/headphoto/659/060/062/48163ca0bb894e89aa390e3beda26099_R_100_100_R5_Q70_D.jpg","userName":"aidie","reviewedCount":6},"reviewDetails":{"reviewScore":{"score":"4","scoreMax":"5","scoreDescription":""},"reviewContent":"房间看上去很高大上  就是房间里放的水果都快发霉了  这个有点调档  其他的都非常好  吧台服务也很好","releaseDate":"2019-06-16","travelType":"家庭亲子","roomType":"特价大床房","checkInDate":"2019-04-29","feedbackList":[{"reviewId":"365863515","type":3,"createDate":"2019-06-22","content":"尊敬的宾客：您好！感谢您选择入住温州荣欣楼大酒店，感谢您对我们服务的认可，期待您的再次光临！"}],"sourceText":""},"reviewId":"364997465","helpfulCount":0,"markUseful":true,"showFold":false},{"userProfile":{"avatarUrl":"//ak-d.tripcdn.com/images/Z80t11000000r972a6DE7_R_100_100_R5_Q70_D.jpg","userName":"M292906****","reviewedCount":11},"reviewDetails":{"reviewScore":{"score":"5","scoreMax":"5","scoreDescription":"超棒"},"reviewContent":"早餐很棒 真的很棒～ 房间也很大 挺好的","releaseDate":"2020-06-08","travelType":"情侣出游","roomType":"特价大床房","checkInDate":"2020-01-10","feedbackList":[{"reviewId":"424524063","type":3,"createDate":"2020-07-18","content":"尊敬的宾客，非常感谢您对我们酒店的好评，我们会再接再厉不辜负您的好评。再次感谢您对酒店的肯定，期待再次光临，祝旅途愉快！"}],"sourceText":""},"reviewId":"418785521","helpfulCount":0,"markUseful":true,"showFold":false},{"userProfile":{"avatarUrl":"//ak-d.tripcdn.com/images/Z80p180000013uw9yF21F_R_100_100_R5_Q70_D.jpg","userName":"1895639****","reviewedCount":9},"reviewDetails":{"reviewScore":{"score":"5","scoreMax":"5","scoreDescription":"超棒"},"reviewContent":"干净经济舒适","releaseDate":"2020-09-17","travelType":"其他","roomType":"豪华大床房","checkInDate":"2020-09-16","feedbackList":[{"reviewId":"460867585","type":3,"createDate":"2020-09-26","content":"尊敬的宾客：您好！感谢您选择入住荣欣楼大酒店，您的认可是我们最大的鼓励，我们会继续保持并不断创新与提升各服务细节。期待您的再次光临！"}],"sourceText":""},"reviewId":"459549495","helpfulCount":0,"markUseful":true,"showFold":false},{"userProfile":{"avatarUrl":"//ak-d.tripcdn.com/images/Z80p180000013uw9yF21F_R_100_100_R5_Q70_D.jpg","userName":"letin****","reviewedCount":2},"reviewDetails":{"reviewScore":{"score":"4.3","scoreMax":"5","scoreDescription":""},"reviewContent":"早餐不错，老牌酒店，装修有点旧，但还算干净。","releaseDate":"2019-12-10","travelType":"家庭亲子","roomType":"特价双床房","checkInDate":"2019-11-30","feedbackList":[{"reviewId":"396351773","type":3,"createDate":"2019-12-13","content":"尊敬的贵宾您好!感谢您选择入住荣欣楼大酒店，谢谢您抽出宝贵的时间给我们点评，您的满意是我们最大的动力，期待您的再次光临！"}],"sourceText":""},"reviewId":"395630682","helpfulCount":0,"markUseful":true,"showFold":false},{"userProfile":{"avatarUrl":"//ak-d.tripcdn.com/images/Z80p180000013uw9yF21F_R_100_100_R5_Q70_D.jpg","userName":"M39200****","reviewedCount":1},"reviewDetails":{"reviewScore":{"score":"5","scoreMax":"5","scoreDescription":"超棒"},"reviewContent":"服务很到位","releaseDate":"2020-10-29","travelType":"商务出差","roomType":"特价大床房","checkInDate":"2020-10-27","feedbackList":[{"reviewId":"498070375","type":3,"createDate":"2021-05-13","content":"看到您给我们的全5星好评，小云好开心呀~小云2021年全新装修升级为航空主题酒店，精选优质床品，主打高性价比，期待为您的每一次温州之行提供物超所值的服务~希望您把小云的产品和服务推荐给更多的朋友，小云永远欢迎您回家~"}],"sourceText":""},"reviewId":"466847378","helpfulCount":0,"markUseful":true,"showFold":false},{"userProfile":{"avatarUrl":"//ak-d.tripcdn.com/images/t1/headphoto/857/872/237/edc9e981b00e436a8dcee595001d62fa_R_100_100_R5_Q70_D.jpg","userName":"M301309****","reviewedCount":3},"reviewDetails":{"reviewScore":{"score":"5","scoreMax":"5","scoreDescription":"超棒"},"reviewContent":"还不错 性价比高","releaseDate":"2020-08-04","travelType":"独自旅行","roomType":"特价大床房","checkInDate":"2020-08-01","feedbackList":[{"reviewId":"429482020","type":3,"createDate":"2020-08-16","content":"尊敬的宾客，非常感谢您对我们酒店的好评，我们会再接再厉不辜负您的好评。再次感谢您对酒店的肯定，期待再次光临，祝旅途愉快！"}],"sourceText":""},"reviewId":"427017428","helpfulCount":0,"markUseful":true,"showFold":false},{"userProfile":{"avatarUrl":"//ak-d.tripcdn.com/images/t1/headphoto/463/352/613/9d877effaa3d4bd0b951bb4c60209b3b_R_100_100_R5_Q70_D.jpg","userName":"_WeChat326245****","reviewedCount":1},"reviewDetails":{"reviewScore":{"score":"5","scoreMax":"5","scoreDescription":"超棒"},"reviewContent":"早餐很nice。  酒店位置也挺好找的。\n花了100多的价格，住到了两三百的酒店。\n很值得了，推荐大家","releaseDate":"2019-06-01","travelType":"情侣出游","roomType":"特价大床房","checkInDate":"2019-05-31","feedbackList":[{"reviewId":"364488829","type":3,"createDate":"2019-06-12","content":"尊敬的贵宾您好！感谢您选择入住荣欣楼大酒店。我们始终相信好的口碑一定是从客人最真诚的满意度推荐出来的。我们将不断努力为您及所有宾客提供更佳的入住感受。真诚期待您的再次光临！"}],"sourceText":""},"reviewId":"356050476","helpfulCount":0,"markUseful":true,"showFold":false},{"userProfile":{"avatarUrl":"//ak-d.tripcdn.com/images/0Z80112000832bqwp1106_R_100_100_R5_Q70_D.jpg","userName":"Betterman0431","reviewedCount":37},"reviewDetails":{"reviewScore":{"score":"3","scoreMax":"5","scoreDescription":""},"reviewContent":"挺好的，还不错","releaseDate":"2020-09-10","travelType":"商务出差","roomType":"特价双床房","checkInDate":"2020-09-07","feedbackList":[{"reviewId":"459025232","type":3,"createDate":"2020-09-14","content":"尊敬的贵宾您好!感谢您选择入住荣欣楼大酒店，谢谢您抽出宝贵的时间给我们点评，您的满意是我们最大的动力，期待您的再次光临！"}],"sourceText":""},"reviewId":"458494551","helpfulCount":0,"markUseful":true,"showFold":false},{"userProfile":{"avatarUrl":"//ak-d.tripcdn.com/images/Z8020z000000nd12f89C5_R_100_100_R5_Q70_D.jpg","userName":"E3327****","reviewedCount":6},"reviewDetails":{"reviewScore":{"score":"5","scoreMax":"5","scoreDescription":"超棒"},"reviewContent":"早餐很丰富，价位也很好. 是我在机场附近住的性价比比较好的一家酒店了！","releaseDate":"2019-07-09","travelType":"朋友出游","roomType":"特价大床房","checkInDate":"2019-07-01","feedbackList":[{"reviewId":"368467722","type":3,"createDate":"2019-07-10","content":"尊敬的宾客：您好！感谢您选择入住荣欣楼大酒店，您的认可是我们最大的鼓励，我们会继续保持并不断创新与提升各服务细节。期待您的再次光临！"}],"sourceText":""},"reviewId":"368358012","helpfulCount":0,"markUseful":true,"showFold":false},{"userProfile":{"avatarUrl":"//ak-d.tripcdn.com/images/t1/headphoto/057/777/943/0b93f8268d5546308915f4f9fcaa9483_R_100_100_R5_Q70_D.jpg","userName":"_CFT0227667****","reviewedCount":6},"reviewDetails":{"reviewScore":{"score":"5","scoreMax":"5","scoreDescription":"超棒"},"reviewContent":"卫生干净，物超所值","releaseDate":"2020-06-16","travelType":"商务出差","roomType":"特价大床房","checkInDate":"2020-06-12","feedbackList":[{"reviewId":"424523861","type":3,"createDate":"2020-07-18","content":"尊敬的宾客，非常感谢您对我们酒店的好评，我们会再接再厉不辜负您的好评。再次感谢您对酒店的肯定，期待再次光临，祝旅途愉快！"}],"sourceText":""},"reviewId":"419924556","helpfulCount":0,"markUseful":true,"showFold":false},{"userProfile":{"avatarUrl":"//ak-d.tripcdn.com/images/Z80p180000013uw9yF21F_R_100_100_R5_Q70_D.jpg","userName":"1586876****","reviewedCount":16},"reviewDetails":{"reviewScore":{"score":"5","scoreMax":"5","scoreDescription":"超棒"},"reviewContent":"比较高档大气","releaseDate":"2020-10-22","travelType":"商务出差","roomType":"特价双床房","checkInDate":"2020-08-19","feedbackList":[{"reviewId":"468986962","type":3,"createDate":"2020-11-10","content":"尊敬的贵宾您好！感谢您选择入住荣欣楼大酒店并分享您的入住体验。感谢您一如既往的支持，我们将不断努力为您及所有宾客提供更佳的入住感受。真诚期待您的再次光临！"}],"sourceText":""},"reviewId":"465659482","helpfulCount":0,"markUseful":true,"showFold":false},{"userProfile":{"avatarUrl":"//ak-d.tripcdn.com/images/0Z84d120008oft1oj66E5_R_100_100_R5_Q70_D.jpg","userName":"德尼王导","reviewedCount":12},"reviewDetails":{"reviewScore":{"score":"5","scoreMax":"5","scoreDescription":"超棒"},"reviewContent":"还可以。比较方便","releaseDate":"2020-09-06","travelType":"商务出差","roomType":"特价大床房","checkInDate":"2020-07-01","feedbackList":[{"reviewId":"459025261","type":3,"createDate":"2020-09-14","content":"尊敬的贵宾您好!感谢您选择入住荣欣楼大酒店，谢谢您抽出宝贵的时间给我们点评，您的满意是我们最大的动力，期待您的再次光临！"}],"sourceText":""},"reviewId":"452180910","helpfulCount":0,"markUseful":true,"showFold":false},{"userProfile":{"avatarUrl":"//ak-d.tripcdn.com/images/Z80p180000013uw9yF21F_R_100_100_R5_Q70_D.jpg","userName":"1388607****","reviewedCount":8},"reviewDetails":{"reviewScore":{"score":"5","scoreMax":"5","scoreDescription":"超棒"},"reviewContent":"房间比较大，离机场也比较近，比较方便，前台服务热情，总体是不错的！","releaseDate":"2019-07-09","travelType":"商务出差","roomType":"特价大床房","checkInDate":"2019-07-04","feedbackList":[{"reviewId":"368467660","type":3,"createDate":"2019-07-10","content":"尊敬的宾客：您好！感谢您选择入住温州荣欣楼大酒店，感谢您对我们服务的认可，期待您的再次光临！"}],"sourceText":""},"reviewId":"368326027","helpfulCount":0,"markUseful":true,"showFold":false},{"userProfile":{"avatarUrl":"//ak-d.tripcdn.com/images/Z80p180000013uw9yF21F_R_100_100_R5_Q70_D.jpg","userName":"1860536****","reviewedCount":25},"reviewDetails":{"reviewScore":{"score":"5","scoreMax":"5","scoreDescription":"超棒"},"reviewContent":"非常高，去了还要选他，能见到空姐与空少","releaseDate":"2020-03-12","travelType":"商务出差","roomType":"特价大床房","checkInDate":"2019-11-10","feedbackList":[{"reviewId":"412110649","type":3,"createDate":"2020-03-29","content":"尊敬的贵宾您好!感谢您选择入住荣欣楼大酒店，谢谢您抽出宝贵的时间给我们点评，您的满意是我们最大的动力，期待您的再次光临！"}],"sourceText":""},"reviewId":"411015982","helpfulCount":0,"markUseful":true,"showFold":false},{"userProfile":{"avatarUrl":"//ak-d.tripcdn.com/images/Z80o180000013ulur1D76_R_100_100_R5_Q70_D.jpg","userName":"M412971****","reviewedCount":1},"reviewDetails":{"reviewScore":{"score":"5","scoreMax":"5","scoreDescription":"超棒"},"reviewContent":"非常不的服务","releaseDate":"2020-09-20","travelType":"家庭亲子","roomType":"特价大床房","checkInDate":"2020-08-09","feedbackList":[{"reviewId":"460867612","type":3,"createDate":"2020-09-26","content":"尊敬的宾客：您好！感谢您选择入住荣欣楼大酒店，您的认可是我们最大的鼓励，我们会继续保持并不断创新与提升各服务细节。期待您的再次光临！"}],"sourceText":""},"reviewId":"459910327","helpfulCount":0,"markUseful":true,"showFold":false},{"userProfile":{"avatarUrl":"//ak-d.tripcdn.com/images/t1/headphoto/897/702/674/561c2ed9fa7543f6ae10e9cb051d6aaf_R_100_100_R5_Q70_D.jpg","userName":"行走的冯先生","reviewedCount":13},"reviewDetails":{"reviewScore":{"score":"5","scoreMax":"5","scoreDescription":"超棒"},"reviewContent":"环境不错，距离机场3.5公里打车20块左右。","releaseDate":"2019-12-09","travelType":"商务出差","roomType":"特价大床房","checkInDate":"2019-12-08","feedbackList":[{"reviewId":"396351852","type":3,"createDate":"2019-12-13","content":"尊敬的贵宾您好!感谢您选择入住荣欣楼大酒店，谢谢您抽出宝贵的时间给我们点评，您的满意是我们最大的动力，期待您的再次光临！"}],"sourceText":""},"reviewId":"395501614","helpfulCount":0,"markUseful":true,"showFold":false},{"userProfile":{"avatarUrl":"//ak-d.tripcdn.com/images/zc0p170000011d1zy24F3_R_100_100_R5_Q70_D.jpg","userName":"念夕1208","reviewedCount":3},"reviewDetails":{"reviewScore":{"score":"4","scoreMax":"5","scoreDescription":""},"reviewContent":"被子有点潮，屋里有霉味，开窗通完风会好一点。","releaseDate":"2019-10-06","travelType":"家庭亲子","roomType":"豪华双床房","checkInDate":"2019-10-05","feedbackList":[{"reviewId":"385684487","type":3,"createDate":"2019-10-17","content":"尊敬的贵宾您好!感谢您选择入住荣欣楼大酒店，谢谢您抽出宝贵的时间给我们点评，对于您提出的问题，我们已做整改，真诚期待您的再次光临，希望带给您一个完美的入住体验。"}],"sourceText":""},"reviewId":"383758207","helpfulCount":0,"markUseful":true,"showFold":false},{"userProfile":{"avatarUrl":"//ak-d.tripcdn.com/images/t1/headphoto/164/424/952/04eab99bd26f47acadef4fd3f95b9f37_R_100_100_R5_Q70_D.jpg","userName":"萨加玛塔国家公园燕铁木儿","reviewedCount":7},"reviewDetails":{"reviewScore":{"score":"5","scoreMax":"5","scoreDescription":"超棒"},"reviewContent":"酒店提供免费接机服务，很方便，服务也很专业。","releaseDate":"2019-12-22","travelType":"独自旅行","roomType":"特价大床房","checkInDate":"2019-10-06","feedbackList":[{"reviewId":"412109301","type":3,"createDate":"2020-03-29","content":"尊敬的贵宾您好！感谢您选择入住荣欣楼大酒店。我们始终相信好的口碑一定是从客人最真诚的满意度推荐出来的。我们将不断努力为您及所有宾客提供更佳的入住感受。真诚期待您的再次光临！"}],"sourceText":""},"reviewId":"398324431","helpfulCount":0,"markUseful":true,"showFold":false},{"userProfile":{"avatarUrl":"//ak-d.tripcdn.com/images/Z80p180000013uw9yF21F_R_100_100_R5_Q70_D.jpg","userName":"320013****","reviewedCount":33},"reviewDetails":{"reviewScore":{"score":"5","scoreMax":"5","scoreDescription":"超棒"},"reviewContent":"非常不错！","releaseDate":"2020-11-17","travelType":"商务出差","roomType":"特价大床房","checkInDate":"2020-11-16","feedbackList":[{"reviewId":"498070514","type":3,"createDate":"2021-05-13","content":"看到您给我们的全5星好评，小云好开心呀~小云2021年全新装修升级为航空主题酒店，精选优质床品，主打高性价比，期待为您的每一次温州之行提供物超所值的服务~希望您把小云的产品和服务推荐给更多的朋友，小云永远欢迎您回家~"}],"sourceText":""},"reviewId":"470047399","helpfulCount":0,"markUseful":true,"showFold":false},{"userProfile":{"avatarUrl":"//ak-d.tripcdn.com/images/Z80s10000000p27qc3F86_R_100_100_R5_Q70_D.jpg","userName":"哒哒哒西八","reviewedCount":2},"reviewDetails":{"reviewScore":{"score":"4.8","scoreMax":"5","scoreDescription":"棒"},"reviewContent":"总体挺好的","releaseDate":"2020-09-14","travelType":"其他","roomType":"特价大床房","checkInDate":"2020-09-12","feedbackList":[{"reviewId":"460867336","type":3,"createDate":"2020-09-26","content":"尊敬的贵宾您好!感谢您选择入住荣欣楼大酒店，谢谢您抽出宝贵的时间给我们点评，您的满意是我们最大的动力，期待您的再次光临！"}],"sourceText":""},"reviewId":"459072970","helpfulCount":0,"markUseful":true,"showFold":false},{"userProfile":{"avatarUrl":"//ak-d.tripcdn.com/images/t1/headphoto/973/189/868/dc9925956d9f4505968a091735c787a7_R_100_100_R5_Q70_D.jpg","userName":"yush215998","reviewedCount":77},"reviewDetails":{"reviewScore":{"score":"4","scoreMax":"5","scoreDescription":""},"reviewContent":"因航班到温州机场较晚，故预订了在机场附近的这家酒店。已经住过几次，房间设施还行，就是酒店附近在修路，出行不太方便。早餐一如既往的丰盛。","releaseDate":"2019-01-12","travelType":"商务出差","roomType":"豪华大床房","checkInDate":"2019-01-10","feedbackList":[{"reviewId":"265968655","type":3,"createDate":"2019-01-30","content":"尊敬的贵宾您好！感谢您选择入住荣欣楼大酒店并分享您的入住体验。感谢您一如既往的支持，我们将不断努力为您及所有宾客提供更佳的入住感受。真诚期待您的再次光临！"}],"sourceText":""},"reviewId":"263488360","helpfulCount":0,"markUseful":true,"showFold":false},{"userProfile":{"avatarUrl":"//ak-d.tripcdn.com/images/t1/headphoto/857/872/237/edc9e981b00e436a8dcee595001d62fa_R_100_100_R5_Q70_D.jpg","userName":"M34176****","reviewedCount":16},"reviewDetails":{"reviewScore":{"score":"5","scoreMax":"5","scoreDescription":"超棒"},"reviewContent":"服务好，位置好","releaseDate":"2020-10-21","travelType":"商务出差","roomType":"特价双床房","checkInDate":"2020-07-16","feedbackList":[{"reviewId":"468986572","type":3,"createDate":"2020-11-10","content":"尊敬的宾客：您好！感谢您选择入住温州荣欣楼大酒店，感谢您对我们服务的认可，期待您的再次光临！"}],"sourceText":""},"reviewId":"465431739","helpfulCount":0,"markUseful":true,"showFold":false},{"userProfile":{"avatarUrl":"//ak-d.tripcdn.com/images/Z80l1f000001gqkwkB7DA_R_100_100_R5_Q70_D.jpg","userName":"万能蛋糕","reviewedCount":11},"reviewDetails":{"reviewScore":{"score":"5","scoreMax":"5","scoreDescription":"超棒"},"reviewContent":"商务酒店么 都不差","releaseDate":"2020-05-04","travelType":"商务出差","roomType":"特价双床房","checkInDate":"2020-04-30","feedbackList":[{"reviewId":"418049248","type":3,"createDate":"2020-06-02","content":"尊敬的贵宾您好!感谢您选择入住荣欣楼大酒店，谢谢您抽出宝贵的时间给我们点评，您的满意是我们最大的动力，期待您的再次光临！"}],"sourceText":""},"reviewId":"415254454","helpfulCount":0,"markUseful":true,"showFold":false},{"userProfile":{"avatarUrl":"//ak-d.tripcdn.com/images/t1/headphoto/293/406/308/22631089f44a497495c005fce85f6a6f_R_100_100_R5_Q70_D.jpg","userName":"M269960****","reviewedCount":16},"reviewDetails":{"reviewScore":{"score":"5","scoreMax":"5","scoreDescription":"超棒"},"reviewContent":"交通便利，环境好","releaseDate":"2020-10-05","travelType":"其他","roomType":"豪华双床房","checkInDate":"2020-06-03","feedbackList":[{"reviewId":"463862694","type":3,"createDate":"2020-10-12","content":"尊敬的宾客：您好！感谢您选择入住荣欣楼大酒店，您的认可是我们最大的鼓励，我们会继续保持并不断创新与提升各服务细节。期待您的再次光临！"}],"sourceText":""},"reviewId":"462358520","helpfulCount":0,"markUseful":true,"showFold":false},{"userProfile":{"avatarUrl":"//ak-d.tripcdn.com/images/t1/headphoto/857/872/237/edc9e981b00e436a8dcee595001d62fa_R_100_100_R5_Q70_D.jpg","userName":"M297630****","reviewedCount":56},"reviewDetails":{"reviewScore":{"score":"3.3","scoreMax":"5","scoreDescription":""},"reviewContent":"酒店比较老","releaseDate":"2020-09-03","travelType":"商务出差","roomType":"特价双床房","checkInDate":"2020-08-30","feedbackList":[{"reviewId":"459026436","type":3,"createDate":"2020-09-14","content":"尊敬的宾客：您好！感谢您选择入住荣欣楼大酒店，很遗憾没能带给您一个完美的入住体验，我们将不断努力为您及所有宾客提供更佳的入住感受。真诚期待您的再次光临！"}],"sourceText":""},"reviewId":"451850091","helpfulCount":0,"markUseful":true,"showFold":false},{"userProfile":{"avatarUrl":"//ak-d.tripcdn.com/images/Z80h180000013xc9e3F64_R_100_100_R5_Q70_D.jpg","userName":"hannah1","reviewedCount":1},"reviewDetails":{"reviewScore":{"score":"4.5","scoreMax":"5","scoreDescription":"不错"},"reviewContent":"酒店看着离龙港机场很近，走路肯定要40分钟了，打的就10分钟，被司机难堪掉了，酒店前面在修路，师傅直接让我下车走了三四百米，大晚上吃了一路灰。酒店的早餐很丰富，大床房房间很大，空调一开一关声音很大，后来直接关了。另外早上安排送机，既然规定8点钟走，7点40分就开始崔我，我7.50分到达前台，前台说了一句“就等我，等我了很久”。听了就不乐意了，我又没有迟到。携程唯一不好就是不能退，改也很麻烦，然后发票必须携程上自费申请。","releaseDate":"2018-12-28","travelType":"商务出差","roomType":"豪华大床房","checkInDate":"2018-12-26","feedbackList":[{"reviewId":"262655496","type":3,"createDate":"2019-01-05","content":"尊敬的宾客：您好！感谢您选择入住荣欣楼大酒店，很遗憾没能带给您一个完美的入住体验，宾客的需求就是我们的责任，宾客的满意就是我们最大的心愿，我们会不断总结，努力做得更好，真诚期待您的再次光临！"}],"sourceText":""},"reviewId":"261615047","helpfulCount":0,"markUseful":true,"showFold":false},{"userProfile":{"avatarUrl":"//ak-d.tripcdn.com/images/Z80p180000013uw9yF21F_R_100_100_R5_Q70_D.jpg","userName":"320354****","reviewedCount":1},"reviewDetails":{"reviewScore":{"score":"4.3","scoreMax":"5","scoreDescription":""},"reviewContent":"挺好的，不错","releaseDate":"2020-12-07","travelType":"家庭亲子","roomType":"特价双床房","checkInDate":"2020-08-19","feedbackList":[{"reviewId":"493061006","type":3,"createDate":"2021-04-16","content":"尊敬的宾客您好！非常感谢您的入住与赞赏~小云2021年全新装修升级为航空主题酒店，精选优质床品，主打高性价比，期待为您的每一次温州之行提供物超所值的服务~希望您可以把小云推荐给更多的朋友，小云永远欢迎您回家呀~"}],"sourceText":""},"reviewId":"472974052","helpfulCount":0,"markUseful":true,"showFold":false},{"userProfile":{"avatarUrl":"//ak-d.tripcdn.com/images/Z80p180000013uw9yF21F_R_100_100_R5_Q70_D.jpg","userName":"E0271****","reviewedCount":11},"reviewDetails":{"reviewScore":{"score":"5","scoreMax":"5","scoreDescription":"超棒"},"reviewContent":"适合商务出行，零点之前可以接机，环境可以，交通方便，性价比比较高。","releaseDate":"2019-05-27","travelType":"商务出差","roomType":"特价大床房","checkInDate":"2019-05-25","feedbackList":[{"reviewId":"352817947","type":3,"createDate":"2019-05-31","content":"尊敬的贵宾您好！感谢您选择入住荣欣楼大酒店。我们始终相信好的口碑一定是从客人最真诚的满意度推荐出来的。我们将不断努力为您及所有宾客提供更佳的入住感受。真诚期待您的再次光临！"}],"sourceText":""},"reviewId":"341930362","helpfulCount":0,"markUseful":true,"showFold":false},{"userProfile":{"avatarUrl":"//ak-d.tripcdn.com/images/Z80v0w000000kf23hE97E_R_100_100_R5_Q70_D.jpg","userName":"M276611****","reviewedCount":5},"reviewDetails":{"reviewScore":{"score":"4.3","scoreMax":"5","scoreDescription":""},"reviewContent":"酒店离温州龙湾机场很近，服务态度很好，设施齐全，早餐也不错，门口专门有人帮忙提行李，早上还能安排送机服务。","releaseDate":"2018-09-01","travelType":"家庭亲子","roomType":"行政双床房","checkInDate":"2018-08-30","reviewUpdateImages":["//ak-d.tripcdn.com/images/230d0w000000k2jf07B66_R_150_150_R5_Q70_D.jpg","//ak-d.tripcdn.com/images/23040w000000k302u43C4_R_150_150_R5_Q70_D.jpg","//ak-d.tripcdn.com/images/23050w000000k6iy15F30_R_150_150_R5_Q70_D.jpg"],"feedbackList":[{"reviewId":"243840457","type":3,"createDate":"2018-09-03","content":"尊敬的宾客：您好！感谢您选择入住温州荣欣楼大酒店，感谢您对我们服务的认可，宾客的需求就是我们的责任，宾客的满意就是我们最大的心愿，真诚期待您的再次光临！"}],"sourceText":""},"reviewId":"243292331","helpfulCount":0,"markUseful":true,"showFold":false},{"userProfile":{"avatarUrl":"//ak-d.tripcdn.com/images/Z80f1a0000019cp8r508F_R_100_100_R5_Q70_D.jpg","userName":"无为而为者","reviewedCount":14},"reviewDetails":{"reviewScore":{"score":"5","scoreMax":"5","scoreDescription":"超棒"},"reviewContent":"离机场不太远的性价比高的选择。","releaseDate":"2019-11-14","travelType":"独自旅行","roomType":"特价大床房","checkInDate":"2019-11-12","feedbackList":[{"reviewId":"396350671","type":3,"createDate":"2019-12-13","content":"尊敬的贵宾您好!感谢您选择入住荣欣楼大酒店，谢谢您抽出宝贵的时间给我们点评，您的满意是我们最大的动力，期待您的再次光临！"}],"sourceText":""},"reviewId":"391194691","helpfulCount":0,"markUseful":true,"showFold":false},{"userProfile":{"avatarUrl":"//ak-d.tripcdn.com/images/t1/headphoto/207/494/838/fa687736cf3f484480526cfc0eb6c073_R_100_100_R5_Q70_D.jpg","userName":"小鱼123121","reviewedCount":2},"reviewDetails":{"reviewScore":{"score":"5","scoreMax":"5","scoreDescription":"超棒"},"reviewContent":"没有吃早餐不知道怎么样","releaseDate":"2020-01-21","travelType":"朋友出游","roomType":"豪华单人房","checkInDate":"2020-01-18","feedbackList":[{"reviewId":"412110376","type":3,"createDate":"2020-03-29","content":"尊敬的贵宾您好!感谢您选择入住荣欣楼大酒店，我们酒店早餐很多客人反馈很不错，下次入住时一定要记得品尝，真诚期待您的再次光临！"}],"sourceText":""},"reviewId":"406327536","helpfulCount":0,"markUseful":true,"showFold":false},{"userProfile":{"avatarUrl":"//ak-d.tripcdn.com/images/Z80m14000000x6fv6A5FF_R_100_100_R5_Q70_D.jpg","userName":"咕嘟毒骨轱辘噜","reviewedCount":4},"reviewDetails":{"reviewScore":{"score":"2","scoreMax":"5","scoreDescription":""},"reviewContent":"不咋的感觉","releaseDate":"2020-11-15","travelType":"商务出差","roomType":"行政双床房","checkInDate":"2020-08-04","feedbackList":[{"reviewId":"492664193","type":3,"createDate":"2021-04-14","content":"尊敬的贵宾您好！首先感谢您的光临，小云2021年现已全新装修升级为航空主题酒店，精选优质床品，主打高性价比，小云致力于让每一位宾客享有宾至如归的入住体验，期待为您的每一次温州之行提供物超所值的服务~祝生活愉快~"}],"sourceText":""},"reviewId":"469737120","helpfulCount":0,"markUseful":true,"showFold":false},{"userProfile":{"avatarUrl":"//ak-d.tripcdn.com/images/t1/headphoto/057/777/943/0b93f8268d5546308915f4f9fcaa9483_R_100_100_R5_Q70_D.jpg","userName":"M36086****","reviewedCount":6},"reviewDetails":{"reviewScore":{"score":"5","scoreMax":"5","scoreDescription":"超棒"},"reviewContent":"早餐很好吃，比五星级酒店味道还要好，特别是汤粉干，整整吃了两大碗","releaseDate":"2019-08-06","travelType":"家庭亲子","roomType":"特价大床房","checkInDate":"2019-05-03","feedbackList":[{"reviewId":"373756741","type":3,"createDate":"2019-08-10","content":"尊敬的贵宾您好!感谢您选择入住荣欣楼大酒店，谢谢您抽出宝贵的时间给我们点评，您的满意是我们最大的动力，期待您的再次光临！"}],"sourceText":""},"reviewId":"373027100","helpfulCount":0,"markUseful":true,"showFold":false},{"userProfile":{"avatarUrl":"//ak-d.tripcdn.com/images/t1/headphoto/397/132/243/542067aa29904ae9aca7e88f43eaeb6f_R_100_100_R5_Q70_D.jpg","userName":"_CFT0234781****","reviewedCount":2},"reviewDetails":{"reviewScore":{"score":"5","scoreMax":"5","scoreDescription":"超棒"},"reviewContent":"挺好的 服务好","releaseDate":"2020-06-23","travelType":"独自旅行","roomType":"特价大床房","checkInDate":"2020-06-10","feedbackList":[{"reviewId":"423416599","type":3,"createDate":"2020-07-11","content":"尊敬的宾客，非常感谢您对我们酒店的好评，我们会再接再厉不辜负您的好评。再次感谢您对酒店的肯定，期待再次光临，祝旅途愉快！"}],"sourceText":""},"reviewId":"420741444","helpfulCount":0,"markUseful":true,"showFold":false},{"userProfile":{"avatarUrl":"//ak-d.tripcdn.com/images/t1/headphoto/207/494/838/fa687736cf3f484480526cfc0eb6c073_R_100_100_R5_Q70_D.jpg","userName":"M24922****","reviewedCount":16},"reviewDetails":{"reviewScore":{"score":"5","scoreMax":"5","scoreDescription":"超棒"},"reviewContent":"由于比较偏所以好像住的人不多但环境还是很不错","releaseDate":"2019-07-24","travelType":"商务出差","roomType":"行政大床房","checkInDate":"2019-07-04","feedbackList":[{"reviewId":"373755848","type":3,"createDate":"2019-08-10","content":"尊敬的贵宾您好！非常感谢您选择入住荣欣楼大酒店，我们将不断努力为您及所有宾客提供更佳的入住感受！争取让每位宾客高兴而来，满意而归，真诚期待您的再次光临！"}],"sourceText":""},"reviewId":"370681535","helpfulCount":0,"markUseful":true,"showFold":false},{"userProfile":{"avatarUrl":"//ak-d.tripcdn.com/images/Z80p180000013uw9yF21F_R_100_100_R5_Q70_D.jpg","userName":"M11344****","reviewedCount":41},"reviewDetails":{"reviewScore":{"score":"4.3","scoreMax":"5","scoreDescription":""},"reviewContent":"酒店服务不错，态度好，还帮忙送到机场，应该点赞！设施比较老旧，对于要求不太高的人还适合居住。当时住宿周边在修路，附近基本是小的店铺，没法走走。","releaseDate":"2019-01-13","travelType":"独自旅行","roomType":"豪华大床房","checkInDate":"2018-12-02","feedbackList":[{"reviewId":"265968757","type":3,"createDate":"2019-01-30","content":"尊敬的宾客：您好！感谢您选择入住温州荣欣楼大酒店，感谢您对我们服务的认可，期待您的再次光临！"}],"sourceText":""},"reviewId":"263652200","helpfulCount":0,"markUseful":true,"showFold":false},{"userProfile":{"avatarUrl":"//ak-d.tripcdn.com/images/Z80p15000000yr7ijCF56_R_100_100_R5_Q70_D.jpg","userName":"_WeChat288423****","reviewedCount":11},"reviewDetails":{"reviewScore":{"score":"5","scoreMax":"5","scoreDescription":"超棒"},"reviewContent":"非常好 里面那么多差评搞笑的吧   有那么娇贵吗？\n服务也很好！","releaseDate":"2019-07-02","travelType":"情侣出游","roomType":"豪华大床房","checkInDate":"2019-06-01","feedbackList":[{"reviewId":"368467188","type":3,"createDate":"2019-07-10","content":"尊敬的宾客：您好！感谢您选择入住荣欣楼大酒店，您的认可是我们最大的鼓励，我们会继续保持并不断创新与提升各服务细节。期待您的再次光临！"}],"sourceText":""},"reviewId":"367274557","helpfulCount":0,"markUseful":true,"showFold":false},{"userProfile":{"avatarUrl":"//ak-d.tripcdn.com/images/Z80215000000yo7sa5D1F_R_100_100_R5_Q70_D.jpg","userName":"M286785****","reviewedCount":1},"reviewDetails":{"reviewScore":{"score":"5","scoreMax":"5","scoreDescription":"超棒"},"reviewContent":"位置还不错","releaseDate":"2020-07-31","travelType":"其他","roomType":"特价双床房","checkInDate":"2020-07-22","feedbackList":[{"reviewId":"426410515","type":3,"createDate":"2020-07-31","content":"尊敬的宾客，非常感谢您对我们酒店的好评，我们会再接再厉不辜负您的好评。再次感谢您对酒店的肯定，期待再次光临，祝旅途愉快！"}],"sourceText":""},"reviewId":"426371302","helpfulCount":0,"markUseful":true,"showFold":false},{"userProfile":{"avatarUrl":"//ak-d.tripcdn.com/images/t1/headphoto/699/910/854/683dab66bb374136af9930ea204dfc7e_R_100_100_R5_Q70_D.jpg","userName":"最爱垠垠小公主","reviewedCount":4},"reviewDetails":{"reviewScore":{"score":"5","scoreMax":"5","scoreDescription":"超棒"},"reviewContent":"还可以的兄弟们","releaseDate":"2020-06-01","travelType":"情侣出游","roomType":"特价大床房","checkInDate":"2020-04-26","feedbackList":[{"reviewId":"418048523","type":3,"createDate":"2020-06-02","content":"尊敬的贵宾您好!感谢您选择入住荣欣楼大酒店，谢谢您抽出宝贵的时间给我们点评，您的满意是我们最大的动力，期待您的再次光临！"}],"sourceText":""},"reviewId":"417982439","helpfulCount":0,"markUseful":true,"showFold":false},{"userProfile":{"avatarUrl":"//ak-d.tripcdn.com/images/Z80p180000013uw9yF21F_R_100_100_R5_Q70_D.jpg","userName":"睿智物语","reviewedCount":18},"reviewDetails":{"reviewScore":{"score":"5","scoreMax":"5","scoreDescription":"超棒"},"reviewContent":"早餐超多品种，可以和星级酒店的早餐媲美，早餐居然有虾球。","releaseDate":"2019-05-28","travelType":"商务出差","roomType":"特价大床房","checkInDate":"2019-05-27","feedbackList":[{"reviewId":"352817818","type":3,"createDate":"2019-05-31","content":"尊敬的贵宾您好!感谢您选择入住荣欣楼大酒店，谢谢您抽出宝贵的时间给我们点评，您的满意是我们最大的动力，期待您的再次光临！"}],"sourceText":""},"reviewId":"342203783","helpfulCount":0,"markUseful":true,"showFold":false},{"userProfile":{"avatarUrl":"//ak-d.tripcdn.com/images/zc0l170000011e3741A91_R_100_100_R5_Q70_D.jpg","userName":"千千1237","reviewedCount":32},"reviewDetails":{"reviewScore":{"score":"5","scoreMax":"5","scoreDescription":"超棒"},"reviewContent":"早餐一级棒，房间安静，宽敞，还会来的","releaseDate":"2019-10-04","travelType":"家庭亲子","roomType":"豪华双床房","checkInDate":"2019-10-03","feedbackList":[{"reviewId":"385682842","type":3,"createDate":"2019-10-17","content":"尊敬的宾客：您好！感谢您选择入住荣欣楼大酒店，您的认可是我们最大的鼓励，我们会继续保持并不断创新与提升各服务细节。期待您的再次光临！"}],"sourceText":""},"reviewId":"383263758","helpfulCount":0,"markUseful":true,"showFold":false},{"userProfile":{"avatarUrl":"//ak-d.tripcdn.com/images/Z80h180000013xc9e3F64_R_100_100_R5_Q70_D.jpg","userName":"1386184****","reviewedCount":5},"reviewDetails":{"reviewScore":{"score":"5","scoreMax":"5","scoreDescription":"超棒"},"reviewContent":"经济又实惠，不错的选择","releaseDate":"2020-01-15","travelType":"商务出差","roomType":"豪华单人房","checkInDate":"2020-01-14","feedbackList":[{"reviewId":"412110496","type":3,"createDate":"2020-03-29","content":"尊敬的贵宾您好!感谢您选择入住荣欣楼大酒店，谢谢您抽出宝贵的时间给我们点评，您的满意是我们最大的动力，期待您的再次光临！"}],"sourceText":""},"reviewId":"405674843","helpfulCount":0,"markUseful":true,"showFold":false},{"userProfile":{"avatarUrl":"//ak-d.tripcdn.com/images/t1/headphoto/177/080/529/285e9abeede347d9a7c1cc5e1b4c9287_R_100_100_R5_Q70_D.jpg","userName":"M237828****","reviewedCount":4},"reviewDetails":{"reviewScore":{"score":"4.3","scoreMax":"5","scoreDescription":""},"reviewContent":"挺好的，赶早班机吃不上早饭","releaseDate":"2019-12-04","travelType":"家庭亲子","roomType":"豪华大床房","checkInDate":"2019-11-27","feedbackList":[{"reviewId":"396351093","type":3,"createDate":"2019-12-13","content":"尊敬的贵宾您好!感谢您选择入住荣欣楼大酒店，谢谢您抽出宝贵的时间给我们点评，您的满意是我们最大的动力，期待您的再次光临！"}],"sourceText":""},"reviewId":"394617808","helpfulCount":0,"markUseful":true,"showFold":false},{"userProfile":{"avatarUrl":"//ak-d.tripcdn.com/images/t1/headphoto/136/299/437/649eb217e3e54746b7a53b8665e14b00_R_100_100_R5_Q70_D.jpg","userName":"M273573****","reviewedCount":1},"reviewDetails":{"reviewScore":{"score":"5","scoreMax":"5","scoreDescription":"超棒"},"reviewContent":"酒店离机场很近，早晨还有送机服务。前台很热情，房间设施很不错。 可惜早晨走得太早，没吃上酒店的早餐。","releaseDate":"2019-01-01","travelType":"商务出差","roomType":"豪华大床房","checkInDate":"2018-12-30","feedbackList":[{"reviewId":"262279409","type":3,"createDate":"2019-01-02","content":"尊敬的宾客：您好！感谢您选择入住温州荣欣楼大酒店，感谢您对我们服务的认可，期待您的再次光临！"}],"sourceText":""},"reviewId":"262089265","helpfulCount":0,"markUseful":true,"showFold":false},{"userProfile":{"avatarUrl":"//ak-d.tripcdn.com/images/Z80o180000013ulur1D76_R_100_100_R5_Q70_D.jpg","userName":"M386494****","reviewedCount":3},"reviewDetails":{"reviewScore":{"score":"3","scoreMax":"5","scoreDescription":""},"reviewContent":"比较老旧，位置偏","releaseDate":"2020-04-19","travelType":"独自旅行","roomType":"豪华大床房","checkInDate":"2020-04-17","feedbackList":[{"reviewId":"476620552","type":3,"createDate":"2021-01-02","content":"尊敬的贵宾您好!感谢您选择入住荣欣楼大酒店，谢谢您抽出宝贵的时间给我们点评，很遗憾没能带给您一个完美的入住体验，我们会不断改进，努力做得更好，真诚期待您的再次光临！"}],"sourceText":""},"reviewId":"413917732","helpfulCount":0,"markUseful":true,"showFold":false}],"ReviewFilterList":[{"name":"全部","id":"1","type":"commonTheme","count":"587"},{"name":"推荐","id":"2","type":"commonTheme","count":"557"},{"name":"差评","id":"3","type":"commonTheme","count":"21"},{"name":"有图","id":"4","type":"commonTheme","count":"25"},{"name":"视频","id":"5","type":"commonTheme","count":"5"},{"name":"有图/视频","id":"6","type":"commonTheme","count":"30"},{"name":"早餐很棒","id":"70","type":"tagTheme","count":"93"},{"name":"服务很好","id":"81","type":"tagTheme","count":"80"},{"name":"去机场方便","id":"94","type":"tagTheme","count":"61"},{"name":"性价比高","id":"58","type":"tagTheme","count":"52"},{"name":"还想再住","id":"149","type":"tagTheme","count":"22"},{"name":"房间很大","id":"29","type":"tagTheme","count":"13"},{"name":"适合带孩子","id":"134","type":"tagTheme","count":"8"},{"name":"有异味","id":"5008","type":"tagTheme","count":"6"},{"name":"所有房型","type":"roomType","count":"486"},{"name":"特价大床房","id":"1","type":"roomType","count":"155"},{"name":"特价双床房","id":"2","type":"roomType","count":"97"},{"name":"豪华大床房","id":"3","type":"roomType","count":"80"},{"name":"豪华双床房","id":"4","type":"roomType","count":"60"},{"name":"行政双床房","id":"5","type":"roomType","count":"10"},{"name":"行政大床房","id":"6","type":"roomType","count":"10"},{"name":"豪华套房","id":"7","type":"roomType","count":"10"},{"name":"所有出游类型","type":"reviewTag"},{"name":"商务出差","id":"10","type":"reviewTag","count":"275"},{"name":"家庭亲子","id":"30","type":"reviewTag","count":"44"},{"name":"独自旅行","id":"50","type":"reviewTag","count":"33"},{"name":"代人预订","id":"60","type":"reviewTag","count":"10"},{"name":"情侣出游","id":"70","type":"reviewTag","count":"24"},{"name":"朋友出游","id":"40","type":"reviewTag","count":"27"},{"name":"其他","id":"0","type":"reviewTag","count":"165"}]},"ErrorCode":0}